[
  {
    "i": 0,
    "heading": "Unlock the Power of Cloud: Build, Run & Manage App",
    "subheads": [],
    "height": 672,
    "bg": "rgba(0, 0, 0, 0)",
    "bgImg": "",
    "type": {
      "slider": false,
      "tabs": false,
      "flipBox": false,
      "form": false,
      "accordion": false,
      "counter": false,
      "cards": 0
    },
    "nImg": 1,
    "imgs": [
      "/_next/image/"
    ]
  },
  {
    "i": 1,
    "heading": "Folio3 Achieves Microsoft Solution Partner Designa",
    "subheads": [],
    "height": 503,
    "bg": "rgb(255, 255, 255)",
    "bgImg": "",
    "type": {
      "slider": false,
      "tabs": false,
      "flipBox": false,
      "form": false,
      "accordion": false,
      "counter": false,
      "cards": 4
    },
    "nImg": 0,
    "imgs": []
  },
  {
    "i": 2,
    "heading": "Discover Cloud Opportunities",
    "subheads": [
      "Azure Cloud Services"
    ],
    "height": 684,
    "bg": "rgb(245, 248, 254)",
    "bgImg": "",
    "type": {
      "slider": false,
      "tabs": true,
      "flipBox": false,
      "form": false,
      "accordion": false,
      "counter": false,
      "cards": 1
    },
    "nImg": 0,
    "imgs": []
  },
  {
    "i": 3,
    "heading": "",
    "subheads": [
      "Awards &",
      "Recognition"
    ],
    "height": 176,
    "bg": "rgb(0, 33, 127)",
    "bgImg": "",
    "type": {
      "slider": false,
      "tabs": false,
      "flipBox": false,
      "form": false,
      "accordion": false,
      "counter": false,
      "cards": 0
    },
    "nImg": 0,
    "imgs": []
  },
  {
    "i": 4,
    "heading": "Your Next Big Idea Starts in the Cloud",
    "subheads": [
      "Build Scalable Websites Seamle",
      "Innovate Existing and Future A",
      "Build Mobile Experiences for W"
    ],
    "height": 620,
    "bg": "rgb(255, 255, 255)",
    "bgImg": "",
    "type": {
      "slider": false,
      "tabs": false,
      "flipBox": false,
      "form": false,
      "accordion": false,
      "counter": false,
      "cards": 3
    },
    "nImg": 0,
    "imgs": []
  },
  {
    "i": 5,
    "heading": "Scale Your Business with Our Azure Professional Se",
    "subheads": [],
    "height": 411,
    "bg": "rgb(23, 66, 231)",
    "bgImg": "",
    "type": {
      "slider": false,
      "tabs": false,
      "flipBox": false,
      "form": false,
      "accordion": false,
      "counter": false,
      "cards": 0
    },
    "nImg": 0,
    "imgs": []
  },
  {
    "i": 6,
    "heading": "Work With Top Microsoft CSP Experts",
    "subheads": [],
    "height": 676,
    "bg": "rgb(245, 248, 254)",
    "bgImg": "",
    "type": {
      "slider": false,
      "tabs": false,
      "flipBox": false,
      "form": false,
      "accordion": false,
      "counter": false,
      "cards": 1
    },
    "nImg": 0,
    "imgs": []
  },
  {
    "i": 7,
    "heading": "Ensuring Productivity, Agility, & Scalability.",
    "subheads": [
      "Productivity",
      "Agility",
      "Scalability"
    ],
    "height": 434,
    "bg": "rgb(255, 255, 255)",
    "bgImg": "",
    "type": {
      "slider": false,
      "tabs": false,
      "flipBox": false,
      "form": false,
      "accordion": false,
      "counter": false,
      "cards": 0
    },
    "nImg": 0,
    "imgs": []
  },
  {
    "i": 8,
    "heading": "Our Process",
    "subheads": [
      "Schedule a Free Consultation",
      "Choose the Services that’s rig",
      "Meet with your new Senior-Leve",
      "Let the Cloud Empower you"
    ],
    "height": 611,
    "bg": "rgb(245, 248, 254)",
    "bgImg": "",
    "type": {
      "slider": false,
      "tabs": false,
      "flipBox": false,
      "form": false,
      "accordion": false,
      "counter": false,
      "cards": 0
    },
    "nImg": 0,
    "imgs": []
  },
  {
    "i": 9,
    "heading": "Explore Why Businesses Trust Folio3 To Fuel Growth",
    "subheads": [
      "750+ Certified Developers",
      "Cloud-Centric Approach",
      "App Modernization Specialists",
      "1,000+ Clients Worldwide",
      "100+ Applications Supported",
      "24/7 Support and Maintenance"
    ],
    "height": 919,
    "bg": "rgb(245, 248, 254)",
    "bgImg": "",
    "type": {
      "slider": false,
      "tabs": false,
      "flipBox": false,
      "form": false,
      "accordion": false,
      "counter": false,
      "cards": 6
    },
    "nImg": 0,
    "imgs": []
  },
  {
    "i": 10,
    "heading": "Real Results, Real Impact",
    "subheads": [],
    "height": 766,
    "bg": "rgb(245, 248, 254)",
    "bgImg": "",
    "type": {
      "slider": false,
      "tabs": false,
      "flipBox": false,
      "form": false,
      "accordion": false,
      "counter": false,
      "cards": 2
    },
    "nImg": 2,
    "imgs": [
      "/_next/image/",
      "/_next/image/"
    ]
  },
  {
    "i": 11,
    "heading": "Your Common Queries Are Resolved",
    "subheads": [],
    "height": 731,
    "bg": "rgb(255, 255, 255)",
    "bgImg": "",
    "type": {
      "slider": false,
      "tabs": false,
      "flipBox": false,
      "form": false,
      "accordion": false,
      "counter": false,
      "cards": 0
    },
    "nImg": 0,
    "imgs": []
  },
  {
    "i": 12,
    "heading": "Schedule a 1:1 Call Today",
    "subheads": [],
    "height": 683,
    "bg": "rgb(245, 248, 254)",
    "bgImg": "",
    "type": {
      "slider": false,
      "tabs": false,
      "flipBox": false,
      "form": true,
      "accordion": false,
      "counter": false,
      "cards": 1
    },
    "nImg": 0,
    "imgs": []
  }
]