{
  "url": "https://azure.folio3.com/azure-data-analytics/manufacturing-data-analytics/",
  "meta": {
    "title": "Manufacturing Data Analytics | Folio3 Azure Solutions",
    "description": "Unlock manufacturing excellence with AI-powered manufacturing data analytics on Azure. Gain real-time insights for optimized production & efficiency.",
    "canonical": "https://azure.folio3.com/azure-data-analytics/manufacturing-data-analytics/",
    "ogImage": "https://azure.folio3.com/wp-content/uploads/2025/07/drive-manufacturing-excellence-ai-powered-analytics.webp",
    "h1Count": 1
  },
  "sections": [
    {
      "items": [
        {
          "t": "img",
          "src": "https://azure.folio3.com/wp-content/uploads/2022/06/folio3_by_azure.svg",
          "w": 181,
          "h": 40,
          "alt": "Folio3 | Azure"
        },
        {
          "t": "li",
          "text": "Azure Cloud Services"
        },
        {
          "t": "li",
          "text": "Microsoft Fabric Services"
        },
        {
          "t": "li",
          "text": "Data Integration As A Service"
        },
        {
          "t": "li",
          "text": "Data Visualization as a service"
        },
        {
          "t": "li",
          "text": "Data Warehousing as a Service"
        },
        {
          "t": "li",
          "text": "Microsoft Copilot Consulting"
        },
        {
          "t": "li",
          "text": "Copilot Scenario Library"
        },
        {
          "t": "li",
          "text": "RecruitFlow Copilot"
        },
        {
          "t": "li",
          "text": "SmartExpense Agent"
        },
        {
          "t": "li",
          "text": "ITAsset Copilot"
        },
        {
          "t": "li",
          "text": "KubeMonitor Copilot"
        },
        {
          "t": "li",
          "text": "Zammad Ticketing Copilot"
        },
        {
          "t": "li",
          "text": "Microsoft Power Platform"
        },
        {
          "t": "li",
          "text": "Azure Managed Services"
        },
        {
          "t": "li",
          "text": "Intellifabric"
        },
        {
          "t": "li",
          "text": "Logistics and Transport"
        },
        {
          "t": "li",
          "text": "Healthcare"
        },
        {
          "t": "li",
          "text": "Retail"
        },
        {
          "t": "li",
          "text": "Manufacturing"
        },
        {
          "t": "li",
          "text": "Construction"
        },
        {
          "t": "li",
          "text": "Success Stories"
        },
        {
          "t": "li",
          "text": "Blog"
        },
        {
          "t": "li",
          "text": "About Us"
        },
        {
          "t": "li",
          "text": "Contact Us"
        },
        {
          "t": "li",
          "text": "Azure Cloud Services"
        },
        {
          "t": "li",
          "text": "Microsoft Fabric Services"
        },
        {
          "t": "li",
          "text": "Data Integration As A Service"
        },
        {
          "t": "li",
          "text": "Data Visualization as a service"
        },
        {
          "t": "li",
          "text": "Data Warehousing as a Service"
        },
        {
          "t": "li",
          "text": "Microsoft Copilot Consulting"
        },
        {
          "t": "li",
          "text": "Copilot Scenario Library"
        },
        {
          "t": "li",
          "text": "RecruitFlow Copilot"
        },
        {
          "t": "li",
          "text": "SmartExpense Agent"
        },
        {
          "t": "li",
          "text": "ITAsset Copilot"
        },
        {
          "t": "li",
          "text": "KubeMonitor Copilot"
        },
        {
          "t": "li",
          "text": "Zammad Ticketing Copilot"
        },
        {
          "t": "li",
          "text": "Microsoft Power Platform"
        },
        {
          "t": "li",
          "text": "Azure Managed Services"
        },
        {
          "t": "li",
          "text": "Intellifabric"
        },
        {
          "t": "li",
          "text": "Logistics and Transport"
        },
        {
          "t": "li",
          "text": "Healthcare"
        },
        {
          "t": "li",
          "text": "Retail"
        },
        {
          "t": "li",
          "text": "Manufacturing"
        },
        {
          "t": "li",
          "text": "Construction"
        },
        {
          "t": "li",
          "text": "Success Stories"
        },
        {
          "t": "li",
          "text": "Blog"
        },
        {
          "t": "li",
          "text": "About Us"
        },
        {
          "t": "li",
          "text": "Contact Us"
        },
        {
          "t": "li",
          "text": "Talk with Us +1 (408) 412-3813"
        },
        {
          "t": "cta",
          "text": "Get in Touch",
          "href": "/contact-us/"
        }
      ],
      "headings": [],
      "paragraphs": [],
      "listItems": [
        "Azure Cloud Services",
        "Microsoft Fabric Services",
        "Data Integration As A Service",
        "Data Visualization as a service",
        "Data Warehousing as a Service",
        "Microsoft Copilot Consulting",
        "Copilot Scenario Library",
        "RecruitFlow Copilot",
        "SmartExpense Agent",
        "ITAsset Copilot",
        "KubeMonitor Copilot",
        "Zammad Ticketing Copilot",
        "Microsoft Power Platform",
        "Azure Managed Services",
        "Intellifabric",
        "Logistics and Transport",
        "Healthcare",
        "Retail",
        "Manufacturing",
        "Construction",
        "Success Stories",
        "Blog",
        "About Us",
        "Contact Us",
        "Talk with Us +1 (408) 412-3813"
      ],
      "ctas": [
        {
          "text": "Get in Touch",
          "href": "/contact-us/"
        }
      ],
      "images": [
        {
          "src": "https://azure.folio3.com/wp-content/uploads/2022/06/folio3_by_azure.svg",
          "alt": "Folio3 | Azure",
          "w": 181,
          "h": 40
        }
      ]
    },
    {
      "items": [
        {
          "t": "h",
          "tag": "h1",
          "text": "Drive Manufacturing Excellence With AI-Powered Analytics"
        },
        {
          "t": "h",
          "tag": "h2",
          "text": "The all-in-one data analysis, reporting, and AI tools for manufacturers to gain a real-time view of manufacturing operations."
        },
        {
          "t": "cta",
          "text": "CONSULT OUR EXPERTS",
          "href": "#pgForm"
        },
        {
          "t": "img",
          "src": "https://azure.folio3.com/wp-content/uploads/2025/07/drive-manufacturing-excellence-ai-powered-analytics.webp",
          "w": 782,
          "h": 610,
          "alt": ""
        }
      ],
      "headings": [
        {
          "tag": "h1",
          "text": "Drive Manufacturing Excellence With AI-Powered Analytics"
        },
        {
          "tag": "h2",
          "text": "The all-in-one data analysis, reporting, and AI tools for manufacturers to gain a real-time view of manufacturing operations."
        }
      ],
      "paragraphs": [],
      "listItems": [],
      "ctas": [
        {
          "text": "CONSULT OUR EXPERTS",
          "href": "#pgForm"
        }
      ],
      "images": [
        {
          "src": "https://azure.folio3.com/wp-content/uploads/2025/07/drive-manufacturing-excellence-ai-powered-analytics.webp",
          "alt": "",
          "w": 782,
          "h": 610
        }
      ]
    },
    {
      "items": [
        {
          "t": "p",
          "text": "Home » Azure Data Analytics » Manufacturing Data Analytics"
        }
      ],
      "headings": [],
      "paragraphs": [
        "Home » Azure Data Analytics » Manufacturing Data Analytics"
      ],
      "listItems": [],
      "ctas": [],
      "images": []
    },
    {
      "items": [
        {
          "t": "img",
          "src": "https://azure.folio3.com/wp-content/uploads/2024/01/ias-savills-logo.webp",
          "w": 196,
          "h": 92,
          "alt": ""
        },
        {
          "t": "img",
          "src": "https://azure.folio3.com/wp-content/uploads/2024/01/ias-cityu-logo.webp",
          "w": 186,
          "h": 87,
          "alt": ""
        },
        {
          "t": "img",
          "src": "https://azure.folio3.com/wp-content/uploads/2024/01/ias-daraz-logo.webp",
          "w": 190,
          "h": 89,
          "alt": ""
        },
        {
          "t": "img",
          "src": "https://azure.folio3.com/wp-content/uploads/2024/01/ias-rff-logo.webp",
          "w": 196,
          "h": 92,
          "alt": ""
        },
        {
          "t": "img",
          "src": "https://azure.folio3.com/wp-content/uploads/2025/07/slb-1.webp",
          "w": 220,
          "h": 121,
          "alt": ""
        },
        {
          "t": "img",
          "src": "https://azure.folio3.com/wp-content/uploads/2025/07/where-food-comes-from.webp",
          "w": 220,
          "h": 121,
          "alt": ""
        }
      ],
      "headings": [],
      "paragraphs": [],
      "listItems": [],
      "ctas": [],
      "images": [
        {
          "src": "https://azure.folio3.com/wp-content/uploads/2024/01/ias-savills-logo.webp",
          "alt": "",
          "w": 196,
          "h": 92
        },
        {
          "src": "https://azure.folio3.com/wp-content/uploads/2024/01/ias-cityu-logo.webp",
          "alt": "",
          "w": 186,
          "h": 87
        },
        {
          "src": "https://azure.folio3.com/wp-content/uploads/2024/01/ias-daraz-logo.webp",
          "alt": "",
          "w": 190,
          "h": 89
        },
        {
          "src": "https://azure.folio3.com/wp-content/uploads/2024/01/ias-rff-logo.webp",
          "alt": "",
          "w": 196,
          "h": 92
        },
        {
          "src": "https://azure.folio3.com/wp-content/uploads/2025/07/slb-1.webp",
          "alt": "",
          "w": 220,
          "h": 121
        },
        {
          "src": "https://azure.folio3.com/wp-content/uploads/2025/07/where-food-comes-from.webp",
          "alt": "",
          "w": 220,
          "h": 121
        }
      ]
    },
    {
      "items": [
        {
          "t": "h",
          "tag": "h2",
          "text": "Transform Your Operations With Folio3's Manufacturing Analytics Suite"
        },
        {
          "t": "p",
          "text": "The vast amounts of data generated through machines, sensors, supply chain logistics, and quality control is often underutilized and trapped in departmental silos. A manufacturing data analytics solution helps you break down data silos and connect your data from all sources into a single source of truth to drive actionable insights. Folio3 offers a pre-built manufacturing analytics solution with room for customization, providing you with dashboards for real-time data analytics for smart manufacturing systems and gaining deeper insights into the entire production ecosystem."
        },
        {
          "t": "cta",
          "text": "explore now",
          "href": "#pgForm"
        },
        {
          "t": "img",
          "src": "https://azure.folio3.com/wp-content/uploads/2025/07/transform-your-operations-with-folio3-manufacturing-analytics-suite.webp",
          "w": 685,
          "h": 581,
          "alt": ""
        }
      ],
      "headings": [
        {
          "tag": "h2",
          "text": "Transform Your Operations With Folio3's Manufacturing Analytics Suite"
        }
      ],
      "paragraphs": [
        "The vast amounts of data generated through machines, sensors, supply chain logistics, and quality control is often underutilized and trapped in departmental silos. A manufacturing data analytics solution helps you break down data silos and connect your data from all sources into a single source of truth to drive actionable insights. Folio3 offers a pre-built manufacturing analytics solution with room for customization, providing you with dashboards for real-time data analytics for smart manufacturing systems and gaining deeper insights into the entire production ecosystem."
      ],
      "listItems": [],
      "ctas": [
        {
          "text": "explore now",
          "href": "#pgForm"
        }
      ],
      "images": [
        {
          "src": "https://azure.folio3.com/wp-content/uploads/2025/07/transform-your-operations-with-folio3-manufacturing-analytics-suite.webp",
          "alt": "",
          "w": 685,
          "h": 581
        }
      ]
    },
    {
      "items": [
        {
          "t": "p",
          "text": "Achieve better operational visibility and control by leveraging our manufacturing analytics dashboards:"
        },
        {
          "t": "h",
          "tag": "h3",
          "text": "Inventory Management"
        },
        {
          "t": "p",
          "text": "Optimize your production schedules and manage supplies by having clear visibility into your inventory levels, stockouts, and lead times."
        },
        {
          "t": "cta",
          "text": "SEE DASHBOARDS IN ACTION",
          "href": "#pgForm"
        },
        {
          "t": "img",
          "src": "https://azure.folio3.com/wp-content/uploads/2025/07/inventory-management-mda.webp",
          "w": 252,
          "h": 150,
          "alt": ""
        },
        {
          "t": "h",
          "tag": "h3",
          "text": "Production Performance"
        },
        {
          "t": "p",
          "text": "Monitor throughput, cycle times, and machine utilization with real-time data analytics for smart manufacturing systems."
        },
        {
          "t": "cta",
          "text": "SEE DASHBOARDS IN ACTION",
          "href": "#pgForm"
        },
        {
          "t": "img",
          "src": "https://azure.folio3.com/wp-content/uploads/2025/07/production-performance-mda.webp",
          "w": 252,
          "h": 150,
          "alt": ""
        },
        {
          "t": "h",
          "tag": "h3",
          "text": "One-Time & In-Full Production (OTIF)"
        },
        {
          "t": "p",
          "text": "Monitor product delivery performance to oversee if the products are delivered on time and complete."
        },
        {
          "t": "cta",
          "text": "SEE DASHBOARDS IN ACTION",
          "href": "#pgForm"
        },
        {
          "t": "img",
          "src": "https://azure.folio3.com/wp-content/uploads/2025/07/one-time-full-production-mda.webp",
          "w": 252,
          "h": 150,
          "alt": ""
        },
        {
          "t": "h",
          "tag": "h3",
          "text": "Sales Order Analysis"
        },
        {
          "t": "p",
          "text": "Connect sales data with production capabilities to optimize scheduling and boost order fulfillment."
        },
        {
          "t": "cta",
          "text": "SEE DASHBOARDS IN ACTION",
          "href": "#pgForm"
        },
        {
          "t": "img",
          "src": "https://azure.folio3.com/wp-content/uploads/2025/07/sales-order-analysis-mda.webp",
          "w": 252,
          "h": 150,
          "alt": ""
        }
      ],
      "headings": [
        {
          "tag": "h3",
          "text": "Inventory Management"
        },
        {
          "tag": "h3",
          "text": "Production Performance"
        },
        {
          "tag": "h3",
          "text": "One-Time & In-Full Production (OTIF)"
        },
        {
          "tag": "h3",
          "text": "Sales Order Analysis"
        }
      ],
      "paragraphs": [
        "Achieve better operational visibility and control by leveraging our manufacturing analytics dashboards:",
        "Optimize your production schedules and manage supplies by having clear visibility into your inventory levels, stockouts, and lead times.",
        "Monitor throughput, cycle times, and machine utilization with real-time data analytics for smart manufacturing systems.",
        "Monitor product delivery performance to oversee if the products are delivered on time and complete.",
        "Connect sales data with production capabilities to optimize scheduling and boost order fulfillment."
      ],
      "listItems": [],
      "ctas": [
        {
          "text": "SEE DASHBOARDS IN ACTION",
          "href": "#pgForm"
        },
        {
          "text": "SEE DASHBOARDS IN ACTION",
          "href": "#pgForm"
        },
        {
          "text": "SEE DASHBOARDS IN ACTION",
          "href": "#pgForm"
        },
        {
          "text": "SEE DASHBOARDS IN ACTION",
          "href": "#pgForm"
        }
      ],
      "images": [
        {
          "src": "https://azure.folio3.com/wp-content/uploads/2025/07/inventory-management-mda.webp",
          "alt": "",
          "w": 252,
          "h": 150
        },
        {
          "src": "https://azure.folio3.com/wp-content/uploads/2025/07/production-performance-mda.webp",
          "alt": "",
          "w": 252,
          "h": 150
        },
        {
          "src": "https://azure.folio3.com/wp-content/uploads/2025/07/one-time-full-production-mda.webp",
          "alt": "",
          "w": 252,
          "h": 150
        },
        {
          "src": "https://azure.folio3.com/wp-content/uploads/2025/07/sales-order-analysis-mda.webp",
          "alt": "",
          "w": 252,
          "h": 150
        }
      ]
    },
    {
      "items": [
        {
          "t": "h",
          "tag": "h2",
          "text": "Our Comprehensive Manufacturing Analytics Offerings"
        },
        {
          "t": "p",
          "text": "Our expertise in data analytics consulting for manufacturing helps provide a solution tailored to your unique manufacturing business needs. Built on Microsoft Azure cloud infrastructure, our Manufacturing Analytics Suite offers:"
        },
        {
          "t": "h",
          "tag": "h3",
          "text": "Pre-built & Customizable Dashboards"
        },
        {
          "t": "p",
          "text": "Get a head start with our pre-built manufacturing dashboards comprising all standard data points with the flexibility of customizing them to visualize specific KPIs and operational me"
        },
        {
          "t": "h",
          "tag": "h3",
          "text": "Advanced Visualization"
        },
        {
          "t": "p",
          "text": "With a manufacturing data analytics solution, you can create intuitive charts, graphs, and heatmaps, pinpointing anomalies requiring instant attention."
        },
        {
          "t": "h",
          "tag": "h3",
          "text": "Multi-Platform Compatibility"
        },
        {
          "t": "p",
          "text": "Access critical manufacturing insights from anywhere around the floor, executive office, or outside working vicinity using any device."
        },
        {
          "t": "h",
          "tag": "h3",
          "text": "Role-Based Dashboarding"
        },
        {
          "t": "p",
          "text": "Provide relevant, personalized views of data to production managers, quality control teams, executives, and more."
        },
        {
          "t": "h",
          "tag": "h3",
          "text": "Data Consolidation"
        },
        {
          "t": "p",
          "text": "Create a single source of truth for all your big data analytics in manufacturing by integrating data from ERPs, IoT sensors, legacy machines, and supply chain platforms."
        },
        {
          "t": "h",
          "tag": "h3",
          "text": "Actionable Manufacturing Floor Insights"
        },
        {
          "t": "p",
          "text": "From reporting data to generating insights that drive immediate and impactful operational improvements."
        }
      ],
      "headings": [
        {
          "tag": "h2",
          "text": "Our Comprehensive Manufacturing Analytics Offerings"
        },
        {
          "tag": "h3",
          "text": "Pre-built & Customizable Dashboards"
        },
        {
          "tag": "h3",
          "text": "Advanced Visualization"
        },
        {
          "tag": "h3",
          "text": "Multi-Platform Compatibility"
        },
        {
          "tag": "h3",
          "text": "Role-Based Dashboarding"
        },
        {
          "tag": "h3",
          "text": "Data Consolidation"
        },
        {
          "tag": "h3",
          "text": "Actionable Manufacturing Floor Insights"
        }
      ],
      "paragraphs": [
        "Our expertise in data analytics consulting for manufacturing helps provide a solution tailored to your unique manufacturing business needs. Built on Microsoft Azure cloud infrastructure, our Manufacturing Analytics Suite offers:",
        "Get a head start with our pre-built manufacturing dashboards comprising all standard data points with the flexibility of customizing them to visualize specific KPIs and operational me",
        "With a manufacturing data analytics solution, you can create intuitive charts, graphs, and heatmaps, pinpointing anomalies requiring instant attention.",
        "Access critical manufacturing insights from anywhere around the floor, executive office, or outside working vicinity using any device.",
        "Provide relevant, personalized views of data to production managers, quality control teams, executives, and more.",
        "Create a single source of truth for all your big data analytics in manufacturing by integrating data from ERPs, IoT sensors, legacy machines, and supply chain platforms.",
        "From reporting data to generating insights that drive immediate and impactful operational improvements."
      ],
      "listItems": [],
      "ctas": [],
      "images": []
    },
    {
      "items": [
        {
          "t": "h",
          "tag": "h2",
          "text": "The Indispensable Value of BI Reporting for Manufacturers"
        },
        {
          "t": "img",
          "src": "https://azure.folio3.com/wp-content/uploads/2025/07/indispensable-value.webp",
          "w": 706,
          "h": 791,
          "alt": ""
        },
        {
          "t": "img",
          "src": "https://azure.folio3.com/wp-content/uploads/2025/07/operational-efficiency-icon.svg",
          "w": 81,
          "h": 81,
          "alt": " "
        },
        {
          "t": "p",
          "text": "Identify inefficiencies, bottlenecks, and areas for improvement using business intelligence reporting."
        },
        {
          "t": "img",
          "src": "https://azure.folio3.com/wp-content/uploads/2025/07/quality-control-icon.svg",
          "w": 81,
          "h": 81,
          "alt": " "
        },
        {
          "t": "p",
          "text": "Pinpoint root causes of defects and discrepancies by analyzing data from production and quality inspections."
        },
        {
          "t": "img",
          "src": "https://azure.folio3.com/wp-content/uploads/2025/07/optimize-inventory-icon.svg",
          "w": 81,
          "h": 81,
          "alt": " "
        },
        {
          "t": "p",
          "text": "Prevent overstocking or stockouts by gaining insights into demand patterns, production schedules, and material consumption."
        },
        {
          "t": "img",
          "src": "https://azure.folio3.com/wp-content/uploads/2025/07/asset-optimization-icon.svg",
          "w": 81,
          "h": 81,
          "alt": " "
        },
        {
          "t": "p",
          "text": "Extend equipment/asset lifespan by using real-time machine data insights to predict their failures and maintain them."
        },
        {
          "t": "img",
          "src": "https://azure.folio3.com/wp-content/uploads/2025/07/cost-reduction-icon.svg",
          "w": 81,
          "h": 81,
          "alt": " "
        },
        {
          "t": "p",
          "text": "Big data analytics in manufacturing helps uncover areas of waste and inefficiencies in energy consumption."
        }
      ],
      "headings": [
        {
          "tag": "h2",
          "text": "The Indispensable Value of BI Reporting for Manufacturers"
        }
      ],
      "paragraphs": [
        "Identify inefficiencies, bottlenecks, and areas for improvement using business intelligence reporting.",
        "Pinpoint root causes of defects and discrepancies by analyzing data from production and quality inspections.",
        "Prevent overstocking or stockouts by gaining insights into demand patterns, production schedules, and material consumption.",
        "Extend equipment/asset lifespan by using real-time machine data insights to predict their failures and maintain them.",
        "Big data analytics in manufacturing helps uncover areas of waste and inefficiencies in energy consumption."
      ],
      "listItems": [],
      "ctas": [],
      "images": [
        {
          "src": "https://azure.folio3.com/wp-content/uploads/2025/07/indispensable-value.webp",
          "alt": "",
          "w": 706,
          "h": 791
        },
        {
          "src": "https://azure.folio3.com/wp-content/uploads/2025/07/operational-efficiency-icon.svg",
          "alt": " ",
          "w": 81,
          "h": 81
        },
        {
          "src": "https://azure.folio3.com/wp-content/uploads/2025/07/quality-control-icon.svg",
          "alt": " ",
          "w": 81,
          "h": 81
        },
        {
          "src": "https://azure.folio3.com/wp-content/uploads/2025/07/optimize-inventory-icon.svg",
          "alt": " ",
          "w": 81,
          "h": 81
        },
        {
          "src": "https://azure.folio3.com/wp-content/uploads/2025/07/asset-optimization-icon.svg",
          "alt": " ",
          "w": 81,
          "h": 81
        },
        {
          "src": "https://azure.folio3.com/wp-content/uploads/2025/07/cost-reduction-icon.svg",
          "alt": " ",
          "w": 81,
          "h": 81
        }
      ]
    },
    {
      "items": [
        {
          "t": "h",
          "tag": "h2",
          "text": "Covering All Data Analytics Use Cases In Manufacturing"
        },
        {
          "t": "h",
          "tag": "h3",
          "text": "Track OEE Across All Factories"
        },
        {
          "t": "p",
          "text": "Gain a unified view of Overall Equipment Effectiveness (OEE) across multiple plants."
        },
        {
          "t": "h",
          "tag": "h3",
          "text": "Supplier & KPI Management"
        },
        {
          "t": "p",
          "text": "Examine supplier performance and optimize the supply chain for enhanced efficiency."
        },
        {
          "t": "h",
          "tag": "h3",
          "text": "Quality Control"
        },
        {
          "t": "p",
          "text": "Visualize product defect rates, quality tests, and customer feedback to pinpoint quality issues and their root causes."
        },
        {
          "t": "h",
          "tag": "h3",
          "text": "Predictive Maintenance"
        },
        {
          "t": "p",
          "text": "Foresee equipment failures before they take place and transition to proactive maintenance approach instead of relying on reactive repairs."
        },
        {
          "t": "h",
          "tag": "h3",
          "text": "Energy Consumption Optimization"
        },
        {
          "t": "p",
          "text": "Track energy consumption across your manufacturing facility and implement an optimization plan for more efficient usage."
        },
        {
          "t": "h",
          "tag": "h3",
          "text": "Yield Optimization"
        },
        {
          "t": "p",
          "text": "Analyze production parameters to identify factors influencing yield rates, reduce scrap, and improve material utilization."
        },
        {
          "t": "cta",
          "text": "HAVE SOMETHING ELSE IN MIND?",
          "href": "#pgForm"
        }
      ],
      "headings": [
        {
          "tag": "h2",
          "text": "Covering All Data Analytics Use Cases In Manufacturing"
        },
        {
          "tag": "h3",
          "text": "Track OEE Across All Factories"
        },
        {
          "tag": "h3",
          "text": "Supplier & KPI Management"
        },
        {
          "tag": "h3",
          "text": "Quality Control"
        },
        {
          "tag": "h3",
          "text": "Predictive Maintenance"
        },
        {
          "tag": "h3",
          "text": "Energy Consumption Optimization"
        },
        {
          "tag": "h3",
          "text": "Yield Optimization"
        }
      ],
      "paragraphs": [
        "Gain a unified view of Overall Equipment Effectiveness (OEE) across multiple plants.",
        "Examine supplier performance and optimize the supply chain for enhanced efficiency.",
        "Visualize product defect rates, quality tests, and customer feedback to pinpoint quality issues and their root causes.",
        "Foresee equipment failures before they take place and transition to proactive maintenance approach instead of relying on reactive repairs.",
        "Track energy consumption across your manufacturing facility and implement an optimization plan for more efficient usage.",
        "Analyze production parameters to identify factors influencing yield rates, reduce scrap, and improve material utilization."
      ],
      "listItems": [],
      "ctas": [
        {
          "text": "HAVE SOMETHING ELSE IN MIND?",
          "href": "#pgForm"
        }
      ],
      "images": []
    },
    {
      "items": [
        {
          "t": "h",
          "tag": "h2",
          "text": "Features of Our Advanced Manufacturing Data Analytics Suite"
        },
        {
          "t": "h",
          "tag": "h3",
          "text": "OneLake"
        },
        {
          "t": "p",
          "text": "A centralized data storage to minimize data duplication and movement from disparate systems, like sensors, ERPs, etc."
        },
        {
          "t": "h",
          "tag": "h3",
          "text": "Real-Time Monitoring & Predictive Analytics"
        },
        {
          "t": "p",
          "text": "The AI/ML & predictive algorithms to continuously monitor production parameters, detecting faults and forecasting production trends."
        },
        {
          "t": "h",
          "tag": "h3",
          "text": "Custom Models for Analytics"
        },
        {
          "t": "p",
          "text": "Access the tailored models to monitor Overall Equipment Effectiveness (OEE), product quality, and production cycle times."
        },
        {
          "t": "h",
          "tag": "h3",
          "text": "AI & Automation"
        },
        {
          "t": "p",
          "text": "Use the powerful features of integrated Copilot-backed artificial intelligence within the analytics suite to automate your production processes."
        },
        {
          "t": "h",
          "tag": "h3",
          "text": "Notifications & Alerts"
        },
        {
          "t": "p",
          "text": "Get instant alerts for any disturbances caused in your production, exceeding certain threshold limits, so you can quickly respond to such anomalies."
        }
      ],
      "headings": [
        {
          "tag": "h2",
          "text": "Features of Our Advanced Manufacturing Data Analytics Suite"
        },
        {
          "tag": "h3",
          "text": "OneLake"
        },
        {
          "tag": "h3",
          "text": "Real-Time Monitoring & Predictive Analytics"
        },
        {
          "tag": "h3",
          "text": "Custom Models for Analytics"
        },
        {
          "tag": "h3",
          "text": "AI & Automation"
        },
        {
          "tag": "h3",
          "text": "Notifications & Alerts"
        }
      ],
      "paragraphs": [
        "A centralized data storage to minimize data duplication and movement from disparate systems, like sensors, ERPs, etc.",
        "The AI/ML & predictive algorithms to continuously monitor production parameters, detecting faults and forecasting production trends.",
        "Access the tailored models to monitor Overall Equipment Effectiveness (OEE), product quality, and production cycle times.",
        "Use the powerful features of integrated Copilot-backed artificial intelligence within the analytics suite to automate your production processes.",
        "Get instant alerts for any disturbances caused in your production, exceeding certain threshold limits, so you can quickly respond to such anomalies."
      ],
      "listItems": [],
      "ctas": [],
      "images": []
    },
    {
      "items": [
        {
          "t": "h",
          "tag": "h3",
          "text": "Tailor Your Manufacturing Data Analytics Solution With Professionals"
        },
        {
          "t": "p",
          "text": "Folio3, being a Microsoft Solutions Partner and in the business for over 15 years, possesses deep expertise in implementing manufacturing data analytics solutions."
        },
        {
          "t": "cta",
          "text": "GET A CUSTOM SOLUTION PROPOSAL",
          "href": "#pgForm"
        },
        {
          "t": "img",
          "src": "https://azure.folio3.com/wp-content/uploads/2025/07/remote-manufacturing-operations.webp",
          "w": 223,
          "h": 150,
          "alt": ""
        }
      ],
      "headings": [
        {
          "tag": "h3",
          "text": "Tailor Your Manufacturing Data Analytics Solution With Professionals"
        }
      ],
      "paragraphs": [
        "Folio3, being a Microsoft Solutions Partner and in the business for over 15 years, possesses deep expertise in implementing manufacturing data analytics solutions."
      ],
      "listItems": [],
      "ctas": [
        {
          "text": "GET A CUSTOM SOLUTION PROPOSAL",
          "href": "#pgForm"
        }
      ],
      "images": [
        {
          "src": "https://azure.folio3.com/wp-content/uploads/2025/07/remote-manufacturing-operations.webp",
          "alt": "",
          "w": 223,
          "h": 150
        }
      ]
    },
    {
      "items": [
        {
          "t": "h",
          "tag": "h2",
          "text": "Gain Deep Insights into your Manufacturing Business"
        },
        {
          "t": "img",
          "src": "https://azure.folio3.com/wp-content/uploads/2025/07/gain-deep-insights-your-manufacturing-business.webp",
          "w": 233,
          "h": 150,
          "alt": ""
        },
        {
          "t": "p",
          "text": "Unlock the hidden potential within your operational data points:"
        },
        {
          "t": "li",
          "text": "Identify root causes of production bottlenecks."
        },
        {
          "t": "li",
          "text": "Optimize energy consumption across your facilities."
        },
        {
          "t": "li",
          "text": "Predict equipment maintenance needs before costly breakdowns."
        },
        {
          "t": "li",
          "text": "Improve product quality and reduce rework rates."
        },
        {
          "t": "li",
          "text": "Gain end-to-end visibility across your entire supply chain."
        },
        {
          "t": "li",
          "text": "Enhance decision-making with data-driven forecasts."
        },
        {
          "t": "li",
          "text": "Drive continuous improvement initiatives with actionable insights."
        },
        {
          "t": "li",
          "text": "Achieve higher levels of operational efficiency and profitability."
        },
        {
          "t": "cta",
          "text": "REQUEST A CONSULTATION",
          "href": "#pgForm"
        }
      ],
      "headings": [
        {
          "tag": "h2",
          "text": "Gain Deep Insights into your Manufacturing Business"
        }
      ],
      "paragraphs": [
        "Unlock the hidden potential within your operational data points:"
      ],
      "listItems": [
        "Identify root causes of production bottlenecks.",
        "Optimize energy consumption across your facilities.",
        "Predict equipment maintenance needs before costly breakdowns.",
        "Improve product quality and reduce rework rates.",
        "Gain end-to-end visibility across your entire supply chain.",
        "Enhance decision-making with data-driven forecasts.",
        "Drive continuous improvement initiatives with actionable insights.",
        "Achieve higher levels of operational efficiency and profitability."
      ],
      "ctas": [
        {
          "text": "REQUEST A CONSULTATION",
          "href": "#pgForm"
        }
      ],
      "images": [
        {
          "src": "https://azure.folio3.com/wp-content/uploads/2025/07/gain-deep-insights-your-manufacturing-business.webp",
          "alt": "",
          "w": 233,
          "h": 150
        }
      ]
    },
    {
      "items": [
        {
          "t": "h",
          "tag": "h2",
          "text": "Serving All Sorts Of Manufacturing Businesses Worldwide"
        },
        {
          "t": "p",
          "text": "Our manufacturing data analytics expertise has made a global impact and extends across industries:"
        },
        {
          "t": "h",
          "tag": "h3",
          "text": "Pharmaceuticals"
        },
        {
          "t": "h",
          "tag": "h3",
          "text": "Semiconductor"
        },
        {
          "t": "h",
          "tag": "h3",
          "text": "Electronics"
        },
        {
          "t": "h",
          "tag": "h3",
          "text": "Food and Beverage"
        },
        {
          "t": "h",
          "tag": "h3",
          "text": "Chemicals"
        },
        {
          "t": "h",
          "tag": "h3",
          "text": "Oil Refining"
        },
        {
          "t": "h",
          "tag": "h3",
          "text": "Automotive"
        },
        {
          "t": "h",
          "tag": "h3",
          "text": "Cement & Building Materials"
        },
        {
          "t": "cta",
          "text": "learn more",
          "href": "#pgForm"
        }
      ],
      "headings": [
        {
          "tag": "h2",
          "text": "Serving All Sorts Of Manufacturing Businesses Worldwide"
        },
        {
          "tag": "h3",
          "text": "Pharmaceuticals"
        },
        {
          "tag": "h3",
          "text": "Semiconductor"
        },
        {
          "tag": "h3",
          "text": "Electronics"
        },
        {
          "tag": "h3",
          "text": "Food and Beverage"
        },
        {
          "tag": "h3",
          "text": "Chemicals"
        },
        {
          "tag": "h3",
          "text": "Oil Refining"
        },
        {
          "tag": "h3",
          "text": "Automotive"
        },
        {
          "tag": "h3",
          "text": "Cement & Building Materials"
        }
      ],
      "paragraphs": [
        "Our manufacturing data analytics expertise has made a global impact and extends across industries:"
      ],
      "listItems": [],
      "ctas": [
        {
          "text": "learn more",
          "href": "#pgForm"
        }
      ],
      "images": []
    },
    {
      "items": [
        {
          "t": "h",
          "tag": "h3",
          "text": "Awards & Recognization"
        },
        {
          "t": "img",
          "src": "https://azure.folio3.com/wp-content/uploads/2023/11/azure_solution_architect.svg",
          "w": 150,
          "h": 150,
          "alt": "azure_solution_architect.svg"
        },
        {
          "t": "img",
          "src": "https://azure.folio3.com/wp-content/uploads/2023/11/azure_administration.svg",
          "w": 150,
          "h": 150,
          "alt": "azure_administration.svg"
        },
        {
          "t": "img",
          "src": "https://azure.folio3.com/wp-content/uploads/2023/11/AZ-400-104-or-204-Azure-DevOps-Engineer-Expert.svg",
          "w": 150,
          "h": 150,
          "alt": "AZ-400-104-or-204-Azure-DevOps-Engineer-Expert.svg"
        },
        {
          "t": "img",
          "src": "https://azure.folio3.com/wp-content/uploads/2023/11/azure_security_engineer.svg",
          "w": 150,
          "h": 150,
          "alt": "azure_security_engineer.svg"
        },
        {
          "t": "img",
          "src": "https://azure.folio3.com/wp-content/uploads/2023/11/data-analyst.svg",
          "w": 150,
          "h": 150,
          "alt": "data-analyst.svg"
        },
        {
          "t": "img",
          "src": "https://azure.folio3.com/wp-content/uploads/2023/11/azure-data-engineer.svg",
          "w": 151,
          "h": 150,
          "alt": "azure-data-engineer.svg"
        },
        {
          "t": "img",
          "src": "https://azure.folio3.com/wp-content/uploads/2023/11/power_platform_developers.svg",
          "w": 150,
          "h": 150,
          "alt": "power_platform_developers.svg"
        },
        {
          "t": "img",
          "src": "https://azure.folio3.com/wp-content/uploads/2023/11/azure-network-engineer.svg",
          "w": 150,
          "h": 150,
          "alt": "azure-network-engineer.svg"
        },
        {
          "t": "img",
          "src": "https://azure.folio3.com/wp-content/uploads/2023/11/MB-900.svg",
          "w": 150,
          "h": 150,
          "alt": "MB-900.svg"
        },
        {
          "t": "img",
          "src": "https://azure.folio3.com/wp-content/uploads/2023/11/AI-102.svg",
          "w": 150,
          "h": 150,
          "alt": "AI-102.svg"
        },
        {
          "t": "img",
          "src": "https://azure.folio3.com/wp-content/uploads/2023/11/DP-100.svg",
          "w": 150,
          "h": 150,
          "alt": "DP-100.svg"
        },
        {
          "t": "img",
          "src": "https://azure.folio3.com/wp-content/uploads/2023/11/AZ-140.svg",
          "w": 150,
          "h": 150,
          "alt": "AZ-140.svg"
        },
        {
          "t": "img",
          "src": "https://azure.folio3.com/wp-content/uploads/2023/11/azure-stack-hub.svg",
          "w": 151,
          "h": 150,
          "alt": "azure-stack-hub.svg"
        },
        {
          "t": "img",
          "src": "https://azure.folio3.com/wp-content/uploads/2023/11/window-server-hybrid-administration.svg",
          "w": 150,
          "h": 150,
          "alt": "window-server-hybrid-administration.svg"
        },
        {
          "t": "img",
          "src": "https://azure.folio3.com/wp-content/uploads/2023/11/mirosoft_certified_trainer.svg",
          "w": 150,
          "h": 150,
          "alt": "mirosoft_certified_trainer.svg"
        }
      ],
      "headings": [
        {
          "tag": "h3",
          "text": "Awards & Recognization"
        }
      ],
      "paragraphs": [],
      "listItems": [],
      "ctas": [],
      "images": [
        {
          "src": "https://azure.folio3.com/wp-content/uploads/2023/11/azure_solution_architect.svg",
          "alt": "azure_solution_architect.svg",
          "w": 150,
          "h": 150
        },
        {
          "src": "https://azure.folio3.com/wp-content/uploads/2023/11/azure_administration.svg",
          "alt": "azure_administration.svg",
          "w": 150,
          "h": 150
        },
        {
          "src": "https://azure.folio3.com/wp-content/uploads/2023/11/AZ-400-104-or-204-Azure-DevOps-Engineer-Expert.svg",
          "alt": "AZ-400-104-or-204-Azure-DevOps-Engineer-Expert.svg",
          "w": 150,
          "h": 150
        },
        {
          "src": "https://azure.folio3.com/wp-content/uploads/2023/11/azure_security_engineer.svg",
          "alt": "azure_security_engineer.svg",
          "w": 150,
          "h": 150
        },
        {
          "src": "https://azure.folio3.com/wp-content/uploads/2023/11/data-analyst.svg",
          "alt": "data-analyst.svg",
          "w": 150,
          "h": 150
        },
        {
          "src": "https://azure.folio3.com/wp-content/uploads/2023/11/azure-data-engineer.svg",
          "alt": "azure-data-engineer.svg",
          "w": 151,
          "h": 150
        },
        {
          "src": "https://azure.folio3.com/wp-content/uploads/2023/11/power_platform_developers.svg",
          "alt": "power_platform_developers.svg",
          "w": 150,
          "h": 150
        },
        {
          "src": "https://azure.folio3.com/wp-content/uploads/2023/11/azure-network-engineer.svg",
          "alt": "azure-network-engineer.svg",
          "w": 150,
          "h": 150
        },
        {
          "src": "https://azure.folio3.com/wp-content/uploads/2023/11/MB-900.svg",
          "alt": "MB-900.svg",
          "w": 150,
          "h": 150
        },
        {
          "src": "https://azure.folio3.com/wp-content/uploads/2023/11/AI-102.svg",
          "alt": "AI-102.svg",
          "w": 150,
          "h": 150
        },
        {
          "src": "https://azure.folio3.com/wp-content/uploads/2023/11/DP-100.svg",
          "alt": "DP-100.svg",
          "w": 150,
          "h": 150
        },
        {
          "src": "https://azure.folio3.com/wp-content/uploads/2023/11/AZ-140.svg",
          "alt": "AZ-140.svg",
          "w": 150,
          "h": 150
        },
        {
          "src": "https://azure.folio3.com/wp-content/uploads/2023/11/azure-stack-hub.svg",
          "alt": "azure-stack-hub.svg",
          "w": 151,
          "h": 150
        },
        {
          "src": "https://azure.folio3.com/wp-content/uploads/2023/11/window-server-hybrid-administration.svg",
          "alt": "window-server-hybrid-administration.svg",
          "w": 150,
          "h": 150
        },
        {
          "src": "https://azure.folio3.com/wp-content/uploads/2023/11/mirosoft_certified_trainer.svg",
          "alt": "mirosoft_certified_trainer.svg",
          "w": 150,
          "h": 150
        }
      ]
    },
    {
      "items": [
        {
          "t": "h",
          "tag": "h2",
          "text": "Why Choose Folio3?"
        },
        {
          "t": "p",
          "text": "We believe in the power of the cloud to transform businesses and empower people."
        },
        {
          "t": "img",
          "src": "https://azure.folio3.com/wp-content/uploads/2023/06/about_us-mock.webp",
          "w": 200,
          "h": 150,
          "alt": "discover the essence of who we are?"
        },
        {
          "t": "li",
          "text": "Over 15 years in custom software development"
        },
        {
          "t": "li",
          "text": "Microsoft Business Solutions Partner in Cloud Solutions"
        },
        {
          "t": "li",
          "text": "We are a team of professionals, well-versed in industry processes and regulations, as well as the implementation of Azure technologies such as AI/ML, Big Data, and Cloud services."
        }
      ],
      "headings": [
        {
          "tag": "h2",
          "text": "Why Choose Folio3?"
        }
      ],
      "paragraphs": [
        "We believe in the power of the cloud to transform businesses and empower people."
      ],
      "listItems": [
        "Over 15 years in custom software development",
        "Microsoft Business Solutions Partner in Cloud Solutions",
        "We are a team of professionals, well-versed in industry processes and regulations, as well as the implementation of Azure technologies such as AI/ML, Big Data, and Cloud services."
      ],
      "ctas": [],
      "images": [
        {
          "src": "https://azure.folio3.com/wp-content/uploads/2023/06/about_us-mock.webp",
          "alt": "discover the essence of who we are?",
          "w": 200,
          "h": 150
        }
      ]
    },
    {
      "items": [
        {
          "t": "h",
          "tag": "h2",
          "text": "Real Results, Real Impact"
        },
        {
          "t": "p",
          "text": "See How Our Customers Succeed"
        },
        {
          "t": "img",
          "src": "https://azure.folio3.com/wp-content/uploads/2025/07/automating-food-plan-management-saving-time-with-copilot.webp",
          "w": 219,
          "h": 150,
          "alt": ""
        },
        {
          "t": "h",
          "tag": "h3",
          "text": "Automating Food Plan Management & Saving 60% Time with Copilot"
        },
        {
          "t": "p",
          "text": "Automated the food plan creation and management process for the institutional and large-scale catering operations."
        },
        {
          "t": "cta",
          "text": "read more",
          "href": "/copilot-implementation-food-verification/"
        },
        {
          "t": "img",
          "src": "https://azure.folio3.com/wp-content/uploads/2025/07/azure-automate-data-reporting-for-slb-with-data-accuracy.webp",
          "w": 219,
          "h": 150,
          "alt": ""
        },
        {
          "t": "h",
          "tag": "h3",
          "text": "Azure Automate Data Reporting for SLB with 99.9% Data Accuracy"
        },
        {
          "t": "p",
          "text": "Automated the food plan creation and management process for the institutional and large-scale catering operations."
        },
        {
          "t": "cta",
          "text": "read more",
          "href": "/azure-automated-data-reporting-for-slb/"
        },
        {
          "t": "img",
          "src": "https://azure.folio3.com/wp-content/uploads/2025/07/power-bi-dashboards-for-a-food-crop-grower-improving-yield-potential.webp",
          "w": 219,
          "h": 150,
          "alt": ""
        },
        {
          "t": "h",
          "tag": "h3",
          "text": "Power BI Dashboards for a Food Crop Grower, Improving Yield Potential by 12%"
        },
        {
          "t": "p",
          "text": "Transformed financial data analysis and reporting for a private equity firm, enhancing decision-making with robust Azure solutions."
        },
        {
          "t": "cta",
          "text": "read more",
          "href": "/implementing-power-bi-dashboard-for-food-crop-grower/"
        }
      ],
      "headings": [
        {
          "tag": "h2",
          "text": "Real Results, Real Impact"
        },
        {
          "tag": "h3",
          "text": "Automating Food Plan Management & Saving 60% Time with Copilot"
        },
        {
          "tag": "h3",
          "text": "Azure Automate Data Reporting for SLB with 99.9% Data Accuracy"
        },
        {
          "tag": "h3",
          "text": "Power BI Dashboards for a Food Crop Grower, Improving Yield Potential by 12%"
        }
      ],
      "paragraphs": [
        "See How Our Customers Succeed",
        "Automated the food plan creation and management process for the institutional and large-scale catering operations.",
        "Transformed financial data analysis and reporting for a private equity firm, enhancing decision-making with robust Azure solutions."
      ],
      "listItems": [],
      "ctas": [
        {
          "text": "read more",
          "href": "/copilot-implementation-food-verification/"
        },
        {
          "text": "read more",
          "href": "/azure-automated-data-reporting-for-slb/"
        },
        {
          "text": "read more",
          "href": "/implementing-power-bi-dashboard-for-food-crop-grower/"
        }
      ],
      "images": [
        {
          "src": "https://azure.folio3.com/wp-content/uploads/2025/07/automating-food-plan-management-saving-time-with-copilot.webp",
          "alt": "",
          "w": 219,
          "h": 150
        },
        {
          "src": "https://azure.folio3.com/wp-content/uploads/2025/07/azure-automate-data-reporting-for-slb-with-data-accuracy.webp",
          "alt": "",
          "w": 219,
          "h": 150
        },
        {
          "src": "https://azure.folio3.com/wp-content/uploads/2025/07/power-bi-dashboards-for-a-food-crop-grower-improving-yield-potential.webp",
          "alt": "",
          "w": 219,
          "h": 150
        }
      ]
    },
    {
      "items": [
        {
          "t": "h",
          "tag": "h2",
          "text": "Frequently Asked Questions"
        },
        {
          "t": "p",
          "text": "Power BI is a business intelligence tool by Microsoft. End-to-end BI solution for manufacturing data analytics to act as the primary interface for visualizing complex operational data, facilitating manufacturers to monitor KPIs, identify trends, and gain actionable insights from various sources like ERP systems, IoT devices, and production machinery."
        },
        {
          "t": "p",
          "text": "Folio3, a certified Microsoft Solutions Partner with considerable experience in data analytics consulting for manufacturing, customizes Power BI to fit the unique demands of each industrial client. This involves:"
        },
        {
          "t": "li",
          "text": "Integrating data from all of your different production systems (MES, SCADA, ERP, and IoT sensors)."
        },
        {
          "t": "li",
          "text": "Creating custom dashboards and reports that include relevant KPIs for your industry and operational objectives."
        },
        {
          "t": "li",
          "text": "Implementing role-based security ensures that different users only see data relevant to their roles."
        },
        {
          "t": "li",
          "text": "Providing training and continuous assistance to ensure that your staff can properly use the platform."
        },
        {
          "t": "p",
          "text": "Folio3’s Manufacturing Analytics Dashboard provides a variety of advantages, including real-time data analytics for smart manufacturing systems, increased operational efficiency, improved quality control, optimized inventory management, proactive predictive maintenance, significant cost savings, and data-driven decision making. It delivers a complete, unified perspective of the whole production process, resulting in greater productivity and profitability."
        },
        {
          "t": "p",
          "text": "Absolutely. We develop manufacturing data analytics software with flexibility in mind. While we do provide robust pre-built dashboards, we specialize in customizing them to suit your specific production processes, KPIs, and reporting needs. This guarantees that the dashboard gives the precise insights required to make smart business decisions."
        },
        {
          "t": "p",
          "text": "Folio3’s dashboard uses advanced data visualization techniques in Power BI to provide complicated manufacturing data analytics in an understandable and accessible style. This includes interactive charts, graphs, gauges, maps, and bespoke graphics that allow users to immediately detect patterns, highlight abnormalities, and drill down into granular data for more detailed research."
        },
        {
          "t": "p",
          "text": "Yes, our Manufacturing Analytics Dashboard, developed with Microsoft Azure and Power BI, is cross-platform compatible. You can securely access your dashboards and reports from desktop PCs, laptops, tablets, and mobile devices, ensuring that crucial insights are always available, no matter where you are."
        },
        {
          "t": "p",
          "text": "Folio3 creates role-based dashboarding to ensure that every user, from shop floor workers and production managers to quality control specialists and executive leadership, has a customized view of the data that is relevant to their unique duties. This avoids information overload while providing highly focused, actionable manufacturing floor insights relevant to their daily work and strategic goals. This method is critical for effective top-rated AI solutions for real-time data analytics in manufacturing."
        },
        {
          "t": "img",
          "src": "https://azure.folio3.com/wp-content/uploads/2024/01/faq_img.webp",
          "w": 166,
          "h": 150,
          "alt": ""
        }
      ],
      "headings": [
        {
          "tag": "h2",
          "text": "Frequently Asked Questions"
        }
      ],
      "paragraphs": [
        "Power BI is a business intelligence tool by Microsoft. End-to-end BI solution for manufacturing data analytics to act as the primary interface for visualizing complex operational data, facilitating manufacturers to monitor KPIs, identify trends, and gain actionable insights from various sources like ERP systems, IoT devices, and production machinery.",
        "Folio3, a certified Microsoft Solutions Partner with considerable experience in data analytics consulting for manufacturing, customizes Power BI to fit the unique demands of each industrial client. This involves:",
        "Folio3’s Manufacturing Analytics Dashboard provides a variety of advantages, including real-time data analytics for smart manufacturing systems, increased operational efficiency, improved quality control, optimized inventory management, proactive predictive maintenance, significant cost savings, and data-driven decision making. It delivers a complete, unified perspective of the whole production process, resulting in greater productivity and profitability.",
        "Absolutely. We develop manufacturing data analytics software with flexibility in mind. While we do provide robust pre-built dashboards, we specialize in customizing them to suit your specific production processes, KPIs, and reporting needs. This guarantees that the dashboard gives the precise insights required to make smart business decisions.",
        "Folio3’s dashboard uses advanced data visualization techniques in Power BI to provide complicated manufacturing data analytics in an understandable and accessible style. This includes interactive charts, graphs, gauges, maps, and bespoke graphics that allow users to immediately detect patterns, highlight abnormalities, and drill down into granular data for more detailed research.",
        "Yes, our Manufacturing Analytics Dashboard, developed with Microsoft Azure and Power BI, is cross-platform compatible. You can securely access your dashboards and reports from desktop PCs, laptops, tablets, and mobile devices, ensuring that crucial insights are always available, no matter where you are.",
        "Folio3 creates role-based dashboarding to ensure that every user, from shop floor workers and production managers to quality control specialists and executive leadership, has a customized view of the data that is relevant to their unique duties. This avoids information overload while providing highly focused, actionable manufacturing floor insights relevant to their daily work and strategic goals. This method is critical for effective top-rated AI solutions for real-time data analytics in manufacturing."
      ],
      "listItems": [
        "Integrating data from all of your different production systems (MES, SCADA, ERP, and IoT sensors).",
        "Creating custom dashboards and reports that include relevant KPIs for your industry and operational objectives.",
        "Implementing role-based security ensures that different users only see data relevant to their roles.",
        "Providing training and continuous assistance to ensure that your staff can properly use the platform."
      ],
      "ctas": [],
      "images": [
        {
          "src": "https://azure.folio3.com/wp-content/uploads/2024/01/faq_img.webp",
          "alt": "",
          "w": 166,
          "h": 150
        }
      ]
    },
    {
      "items": [
        {
          "t": "h",
          "tag": "h2",
          "text": "What makes us the best choice for Azure cloud service providers?"
        },
        {
          "t": "p",
          "text": "We believe in the power of the cloud to transform businesses and empower people."
        }
      ],
      "headings": [
        {
          "tag": "h2",
          "text": "What makes us the best choice for Azure cloud service providers?"
        }
      ],
      "paragraphs": [
        "We believe in the power of the cloud to transform businesses and empower people."
      ],
      "listItems": [],
      "ctas": [],
      "images": []
    },
    {
      "items": [
        {
          "t": "img",
          "src": "https://azure.folio3.com/wp-content/uploads/2024/08/azure-offices-map-img.webp",
          "w": 283,
          "h": 150,
          "alt": ""
        },
        {
          "t": "h",
          "tag": "h2",
          "text": "Schedule a 1:1 Call Today"
        },
        {
          "t": "h",
          "tag": "h2",
          "text": "Get in touch with our team to solve your Azure queries"
        }
      ],
      "headings": [
        {
          "tag": "h2",
          "text": "Schedule a 1:1 Call Today"
        },
        {
          "tag": "h2",
          "text": "Get in touch with our team to solve your Azure queries"
        }
      ],
      "paragraphs": [],
      "listItems": [],
      "ctas": [],
      "images": [
        {
          "src": "https://azure.folio3.com/wp-content/uploads/2024/08/azure-offices-map-img.webp",
          "alt": "",
          "w": 283,
          "h": 150
        }
      ]
    },
    {
      "items": [
        {
          "t": "img",
          "src": "https://azure.folio3.com/wp-content/uploads/2023/04/azure_logo_ftr.png",
          "w": 300,
          "h": 59,
          "alt": "Azure"
        },
        {
          "t": "h",
          "tag": "h5",
          "text": "US Office"
        },
        {
          "t": "li",
          "text": "160 Bovet Road, Suite # 101, San Mateo, CA 94402 USA"
        },
        {
          "t": "li",
          "text": "Pleasanton, California – 6701 Koll Center Parkway, #250 Pleasanton, CA 94566"
        },
        {
          "t": "li",
          "text": "Tel: +1 408 412-3813"
        },
        {
          "t": "li",
          "text": "Support: +1 (408) 512 1812"
        },
        {
          "t": "h",
          "tag": "h5",
          "text": "UAE OFFICE"
        },
        {
          "t": "li",
          "text": "Dubai, UAE – Dubai Internet City, 1st Floor, Building Number 12, Premises ED 29, Dubai, UAE"
        },
        {
          "t": "li",
          "text": "Tel: +971-55-6540154"
        },
        {
          "t": "li",
          "text": "Tel: +971-04-2505173"
        },
        {
          "t": "h",
          "tag": "h5",
          "text": "UK OFFICE"
        },
        {
          "t": "li",
          "text": "Export House, Cawsey Way, Woking Surrey, GU21 6QX"
        },
        {
          "t": "li",
          "text": "Tel: +44 (0) 14 8361 6611"
        },
        {
          "t": "h",
          "tag": "h5",
          "text": "Mexico Office"
        },
        {
          "t": "li",
          "text": "EPICENTRIA, Avenida Netzahualcóyotl 1597, Ciudad del Sol, Zapopan, Jalisco"
        },
        {
          "t": "h",
          "tag": "h5",
          "text": "Pakistan Office"
        },
        {
          "t": "li",
          "text": "Plot 26, Block B, SMCH Society, Main Shahrah-e-Faisal, Karachi"
        },
        {
          "t": "li",
          "text": "Corporate 7 by Maaksons, Executive Block, Civic Center 1, Gulberg Green, Islamabad"
        },
        {
          "t": "li",
          "text": "First Floor, Blue Mall 8-R, MM Alam Road Gulberg III, Lahore"
        },
        {
          "t": "li",
          "text": "Tel: +92-21-3432 3721-4"
        },
        {
          "t": "h",
          "tag": "h5",
          "text": "Canada Office"
        },
        {
          "t": "li",
          "text": "3080 Yonge Street, Suite 6060, Toronto, Ontario M4N 3N1"
        },
        {
          "t": "li",
          "text": "Tel: +1 408 365 4638"
        },
        {
          "t": "li",
          "text": "Support: +1 (408) 512 1812"
        },
        {
          "t": "h",
          "tag": "h5",
          "text": "Bulgaria Office"
        },
        {
          "t": "li",
          "text": "49 Bacho Kiro Street, Sofia, 1000, Bulgaria"
        },
        {
          "t": "p",
          "text": "© 2026, Folio3 Software Inc., All rights reserved."
        },
        {
          "t": "p",
          "text": "Privacy Policy & Terms of Use Cookie Policy"
        }
      ],
      "headings": [
        {
          "tag": "h5",
          "text": "US Office"
        },
        {
          "tag": "h5",
          "text": "UAE OFFICE"
        },
        {
          "tag": "h5",
          "text": "UK OFFICE"
        },
        {
          "tag": "h5",
          "text": "Mexico Office"
        },
        {
          "tag": "h5",
          "text": "Pakistan Office"
        },
        {
          "tag": "h5",
          "text": "Canada Office"
        },
        {
          "tag": "h5",
          "text": "Bulgaria Office"
        }
      ],
      "paragraphs": [
        "© 2026, Folio3 Software Inc., All rights reserved.",
        "Privacy Policy & Terms of Use Cookie Policy"
      ],
      "listItems": [
        "160 Bovet Road, Suite # 101, San Mateo, CA 94402 USA",
        "Pleasanton, California – 6701 Koll Center Parkway, #250 Pleasanton, CA 94566",
        "Tel: +1 408 412-3813",
        "Support: +1 (408) 512 1812",
        "Dubai, UAE – Dubai Internet City, 1st Floor, Building Number 12, Premises ED 29, Dubai, UAE",
        "Tel: +971-55-6540154",
        "Tel: +971-04-2505173",
        "Export House, Cawsey Way, Woking Surrey, GU21 6QX",
        "Tel: +44 (0) 14 8361 6611",
        "EPICENTRIA, Avenida Netzahualcóyotl 1597, Ciudad del Sol, Zapopan, Jalisco",
        "Plot 26, Block B, SMCH Society, Main Shahrah-e-Faisal, Karachi",
        "Corporate 7 by Maaksons, Executive Block, Civic Center 1, Gulberg Green, Islamabad",
        "First Floor, Blue Mall 8-R, MM Alam Road Gulberg III, Lahore",
        "Tel: +92-21-3432 3721-4",
        "3080 Yonge Street, Suite 6060, Toronto, Ontario M4N 3N1",
        "Tel: +1 408 365 4638",
        "49 Bacho Kiro Street, Sofia, 1000, Bulgaria"
      ],
      "ctas": [],
      "images": [
        {
          "src": "https://azure.folio3.com/wp-content/uploads/2023/04/azure_logo_ftr.png",
          "alt": "Azure",
          "w": 300,
          "h": 59
        }
      ]
    }
  ],
  "images": [
    {
      "src": "https://azure.folio3.com/wp-content/uploads/2022/06/folio3_by_azure.svg",
      "alt": ""
    },
    {
      "src": "https://azure.folio3.com/wp-content/uploads/2025/07/drive-manufacturing-excellence-ai-powered-analytics.webp",
      "alt": ""
    },
    {
      "src": "https://azure.folio3.com/wp-content/uploads/2024/01/ias-savills-logo.webp",
      "alt": ""
    },
    {
      "src": "https://azure.folio3.com/wp-content/uploads/2024/01/ias-cityu-logo.webp",
      "alt": ""
    },
    {
      "src": "https://azure.folio3.com/wp-content/uploads/2024/01/ias-daraz-logo.webp",
      "alt": ""
    },
    {
      "src": "https://azure.folio3.com/wp-content/uploads/2024/01/ias-rff-logo.webp",
      "alt": ""
    },
    {
      "src": "https://azure.folio3.com/wp-content/uploads/2025/07/slb-1.webp",
      "alt": ""
    },
    {
      "src": "https://azure.folio3.com/wp-content/uploads/2025/07/where-food-comes-from.webp",
      "alt": ""
    },
    {
      "src": "https://azure.folio3.com/wp-content/uploads/2025/07/transform-your-operations-with-folio3-manufacturing-analytics-suite.webp",
      "alt": ""
    },
    {
      "src": "https://azure.folio3.com/wp-content/uploads/2025/07/inventory-management-mda.webp",
      "alt": ""
    },
    {
      "src": "https://azure.folio3.com/wp-content/uploads/2025/07/production-performance-mda.webp",
      "alt": ""
    },
    {
      "src": "https://azure.folio3.com/wp-content/uploads/2025/07/one-time-full-production-mda.webp",
      "alt": ""
    },
    {
      "src": "https://azure.folio3.com/wp-content/uploads/2025/07/sales-order-analysis-mda.webp",
      "alt": ""
    },
    {
      "src": "https://azure.folio3.com/wp-content/uploads/2025/07/indispensable-value.webp",
      "alt": ""
    },
    {
      "src": "https://azure.folio3.com/wp-content/uploads/2025/07/operational-efficiency-icon.svg",
      "alt": ""
    },
    {
      "src": "https://azure.folio3.com/wp-content/uploads/2025/07/quality-control-icon.svg",
      "alt": ""
    },
    {
      "src": "https://azure.folio3.com/wp-content/uploads/2025/07/optimize-inventory-icon.svg",
      "alt": ""
    },
    {
      "src": "https://azure.folio3.com/wp-content/uploads/2025/07/asset-optimization-icon.svg",
      "alt": ""
    },
    {
      "src": "https://azure.folio3.com/wp-content/uploads/2025/07/cost-reduction-icon.svg",
      "alt": ""
    },
    {
      "src": "https://azure.folio3.com/wp-content/uploads/2025/07/remote-manufacturing-operations.webp",
      "alt": ""
    },
    {
      "src": "https://azure.folio3.com/wp-content/uploads/2025/07/gain-deep-insights-your-manufacturing-business.webp",
      "alt": ""
    },
    {
      "src": "https://azure.folio3.com/wp-content/uploads/2023/11/azure_solution_architect.svg",
      "alt": ""
    },
    {
      "src": "https://azure.folio3.com/wp-content/uploads/2023/11/azure_administration.svg",
      "alt": ""
    },
    {
      "src": "https://azure.folio3.com/wp-content/uploads/2023/11/AZ-400-104-or-204-Azure-DevOps-Engineer-Expert.svg",
      "alt": ""
    },
    {
      "src": "https://azure.folio3.com/wp-content/uploads/2023/11/azure_security_engineer.svg",
      "alt": ""
    },
    {
      "src": "https://azure.folio3.com/wp-content/uploads/2023/11/data-analyst.svg",
      "alt": ""
    },
    {
      "src": "https://azure.folio3.com/wp-content/uploads/2023/11/azure-data-engineer.svg",
      "alt": ""
    },
    {
      "src": "https://azure.folio3.com/wp-content/uploads/2023/11/power_platform_developers.svg",
      "alt": ""
    },
    {
      "src": "https://azure.folio3.com/wp-content/uploads/2023/11/azure-network-engineer.svg",
      "alt": ""
    },
    {
      "src": "https://azure.folio3.com/wp-content/uploads/2023/11/MB-900.svg",
      "alt": ""
    },
    {
      "src": "https://azure.folio3.com/wp-content/uploads/2023/11/AI-102.svg",
      "alt": ""
    },
    {
      "src": "https://azure.folio3.com/wp-content/uploads/2023/11/DP-100.svg",
      "alt": ""
    },
    {
      "src": "https://azure.folio3.com/wp-content/uploads/2023/11/AZ-140.svg",
      "alt": ""
    },
    {
      "src": "https://azure.folio3.com/wp-content/uploads/2023/11/azure-stack-hub.svg",
      "alt": ""
    },
    {
      "src": "https://azure.folio3.com/wp-content/uploads/2023/11/window-server-hybrid-administration.svg",
      "alt": ""
    },
    {
      "src": "https://azure.folio3.com/wp-content/uploads/2023/11/mirosoft_certified_trainer.svg",
      "alt": ""
    },
    {
      "src": "https://azure.folio3.com/wp-content/uploads/2023/06/about_us-mock.webp",
      "alt": ""
    },
    {
      "src": "https://azure.folio3.com/wp-content/uploads/2025/07/automating-food-plan-management-saving-time-with-copilot.webp",
      "alt": ""
    },
    {
      "src": "https://azure.folio3.com/wp-content/uploads/2025/07/azure-automate-data-reporting-for-slb-with-data-accuracy.webp",
      "alt": ""
    },
    {
      "src": "https://azure.folio3.com/wp-content/uploads/2025/07/power-bi-dashboards-for-a-food-crop-grower-improving-yield-potential.webp",
      "alt": ""
    },
    {
      "src": "https://azure.folio3.com/wp-content/uploads/2024/01/faq_img.webp",
      "alt": ""
    },
    {
      "src": "https://azure.folio3.com/wp-content/uploads/2024/08/azure-offices-map-img.webp",
      "alt": ""
    },
    {
      "src": "https://azure.folio3.com/wp-content/uploads/2023/04/azure_logo_ftr.png",
      "alt": ""
    }
  ],
  "bgImages": [
    "https://azure.folio3.com/wp-content/uploads/2025/07/power-platform-header-bg.webp"
  ]
}