{
  "url": "https://azure.folio3.com/azure-for-retail/",
  "meta": {
    "title": "Azure for Retail - Azure",
    "description": null,
    "canonical": "https://azure.folio3.com/azure-for-retail/",
    "ogImage": "https://azure.folio3.com/wp-content/uploads/2023/11/retail-top-banner-img.webp",
    "h1Count": 1
  },
  "sections": [
    {
      "items": [
        {
          "t": "img",
          "src": "https://azure.folio3.com/wp-content/uploads/2022/06/folio3_by_azure.svg",
          "w": 181,
          "h": 40,
          "alt": "Folio3 | Azure"
        },
        {
          "t": "li",
          "text": "Azure Cloud Services"
        },
        {
          "t": "li",
          "text": "Microsoft Fabric Services"
        },
        {
          "t": "li",
          "text": "Data Integration As A Service"
        },
        {
          "t": "li",
          "text": "Data Visualization as a service"
        },
        {
          "t": "li",
          "text": "Data Warehousing as a Service"
        },
        {
          "t": "li",
          "text": "Microsoft Copilot Consulting"
        },
        {
          "t": "li",
          "text": "Copilot Scenario Library"
        },
        {
          "t": "li",
          "text": "RecruitFlow Copilot"
        },
        {
          "t": "li",
          "text": "SmartExpense Agent"
        },
        {
          "t": "li",
          "text": "ITAsset Copilot"
        },
        {
          "t": "li",
          "text": "KubeMonitor Copilot"
        },
        {
          "t": "li",
          "text": "Zammad Ticketing Copilot"
        },
        {
          "t": "li",
          "text": "Microsoft Power Platform"
        },
        {
          "t": "li",
          "text": "Azure Managed Services"
        },
        {
          "t": "li",
          "text": "Intellifabric"
        },
        {
          "t": "li",
          "text": "Logistics and Transport"
        },
        {
          "t": "li",
          "text": "Healthcare"
        },
        {
          "t": "li",
          "text": "Retail"
        },
        {
          "t": "li",
          "text": "Manufacturing"
        },
        {
          "t": "li",
          "text": "Construction"
        },
        {
          "t": "li",
          "text": "Success Stories"
        },
        {
          "t": "li",
          "text": "Blog"
        },
        {
          "t": "li",
          "text": "About Us"
        },
        {
          "t": "li",
          "text": "Contact Us"
        },
        {
          "t": "li",
          "text": "Azure Cloud Services"
        },
        {
          "t": "li",
          "text": "Microsoft Fabric Services"
        },
        {
          "t": "li",
          "text": "Data Integration As A Service"
        },
        {
          "t": "li",
          "text": "Data Visualization as a service"
        },
        {
          "t": "li",
          "text": "Data Warehousing as a Service"
        },
        {
          "t": "li",
          "text": "Microsoft Copilot Consulting"
        },
        {
          "t": "li",
          "text": "Copilot Scenario Library"
        },
        {
          "t": "li",
          "text": "RecruitFlow Copilot"
        },
        {
          "t": "li",
          "text": "SmartExpense Agent"
        },
        {
          "t": "li",
          "text": "ITAsset Copilot"
        },
        {
          "t": "li",
          "text": "KubeMonitor Copilot"
        },
        {
          "t": "li",
          "text": "Zammad Ticketing Copilot"
        },
        {
          "t": "li",
          "text": "Microsoft Power Platform"
        },
        {
          "t": "li",
          "text": "Azure Managed Services"
        },
        {
          "t": "li",
          "text": "Intellifabric"
        },
        {
          "t": "li",
          "text": "Logistics and Transport"
        },
        {
          "t": "li",
          "text": "Healthcare"
        },
        {
          "t": "li",
          "text": "Retail"
        },
        {
          "t": "li",
          "text": "Manufacturing"
        },
        {
          "t": "li",
          "text": "Construction"
        },
        {
          "t": "li",
          "text": "Success Stories"
        },
        {
          "t": "li",
          "text": "Blog"
        },
        {
          "t": "li",
          "text": "About Us"
        },
        {
          "t": "li",
          "text": "Contact Us"
        },
        {
          "t": "li",
          "text": "Talk with Us +1 (408) 412-3813"
        },
        {
          "t": "cta",
          "text": "Get in Touch",
          "href": "/contact-us/"
        }
      ],
      "headings": [],
      "paragraphs": [],
      "listItems": [
        "Azure Cloud Services",
        "Microsoft Fabric Services",
        "Data Integration As A Service",
        "Data Visualization as a service",
        "Data Warehousing as a Service",
        "Microsoft Copilot Consulting",
        "Copilot Scenario Library",
        "RecruitFlow Copilot",
        "SmartExpense Agent",
        "ITAsset Copilot",
        "KubeMonitor Copilot",
        "Zammad Ticketing Copilot",
        "Microsoft Power Platform",
        "Azure Managed Services",
        "Intellifabric",
        "Logistics and Transport",
        "Healthcare",
        "Retail",
        "Manufacturing",
        "Construction",
        "Success Stories",
        "Blog",
        "About Us",
        "Contact Us",
        "Talk with Us +1 (408) 412-3813"
      ],
      "ctas": [
        {
          "text": "Get in Touch",
          "href": "/contact-us/"
        }
      ],
      "images": [
        {
          "src": "https://azure.folio3.com/wp-content/uploads/2022/06/folio3_by_azure.svg",
          "alt": "Folio3 | Azure",
          "w": 181,
          "h": 40
        }
      ]
    },
    {
      "items": [
        {
          "t": "h",
          "tag": "h1",
          "text": "Re-Imagining the Customer Journey"
        },
        {
          "t": "h",
          "tag": "h2",
          "text": "Improve Your Retail Experience with Personalized Interactions, Enhanced Supply Chain Efficiency, and Redefined Multi Channel Retail Operations using Microsoft Azure."
        },
        {
          "t": "cta",
          "text": "Talk to an Expert",
          "href": "#pgForm"
        },
        {
          "t": "cta",
          "text": "Learn More",
          "href": "#pgForm"
        },
        {
          "t": "img",
          "src": "https://azure.folio3.com/wp-content/uploads/2023/11/retail-top-banner-img.webp",
          "w": 627,
          "h": 546,
          "alt": ""
        }
      ],
      "headings": [
        {
          "tag": "h1",
          "text": "Re-Imagining the Customer Journey"
        },
        {
          "tag": "h2",
          "text": "Improve Your Retail Experience with Personalized Interactions, Enhanced Supply Chain Efficiency, and Redefined Multi Channel Retail Operations using Microsoft Azure."
        }
      ],
      "paragraphs": [],
      "listItems": [],
      "ctas": [
        {
          "text": "Talk to an Expert",
          "href": "#pgForm"
        },
        {
          "text": "Learn More",
          "href": "#pgForm"
        }
      ],
      "images": [
        {
          "src": "https://azure.folio3.com/wp-content/uploads/2023/11/retail-top-banner-img.webp",
          "alt": "",
          "w": 627,
          "h": 546
        }
      ]
    },
    {
      "items": [
        {
          "t": "p",
          "text": "Home » Azure for Retail"
        }
      ],
      "headings": [],
      "paragraphs": [
        "Home » Azure for Retail"
      ],
      "listItems": [],
      "ctas": [],
      "images": []
    },
    {
      "items": [
        {
          "t": "h",
          "tag": "h2",
          "text": "Why leverage Azure Services for Retail"
        },
        {
          "t": "p",
          "text": "Overcome retail landscape challenges and transform your retail business to achieve business growth by leveraging the tools you need to thrive in today’s digital world."
        },
        {
          "t": "h",
          "tag": "h3",
          "text": "Better Understand your Customers"
        },
        {
          "t": "h",
          "tag": "h3",
          "text": "Real-Time Insights"
        },
        {
          "t": "h",
          "tag": "h3",
          "text": "Create Seamless Shopping Experience"
        },
        {
          "t": "h",
          "tag": "h3",
          "text": "Build Resilient Supply Chains"
        },
        {
          "t": "cta",
          "text": "learn more",
          "href": "#pgForm"
        }
      ],
      "headings": [
        {
          "tag": "h2",
          "text": "Why leverage Azure Services for Retail"
        },
        {
          "tag": "h3",
          "text": "Better Understand your Customers"
        },
        {
          "tag": "h3",
          "text": "Real-Time Insights"
        },
        {
          "tag": "h3",
          "text": "Create Seamless Shopping Experience"
        },
        {
          "tag": "h3",
          "text": "Build Resilient Supply Chains"
        }
      ],
      "paragraphs": [
        "Overcome retail landscape challenges and transform your retail business to achieve business growth by leveraging the tools you need to thrive in today’s digital world."
      ],
      "listItems": [],
      "ctas": [
        {
          "text": "learn more",
          "href": "#pgForm"
        }
      ],
      "images": []
    },
    {
      "items": [
        {
          "t": "h",
          "tag": "h2",
          "text": "Major Challenges Faced by Retailers"
        },
        {
          "t": "p",
          "text": "We believe in the power of the cloud to transform businesses and empower people."
        },
        {
          "t": "p",
          "text": "Data stored in silos hinder a comprehensive understanding of operations, market trend, and customer behavior."
        },
        {
          "t": "p",
          "text": "Managing a consistent and seamless experience across various channels like online, mobile, and in-store can be challenging."
        },
        {
          "t": "p",
          "text": "Inaccurate demand forecasting and inefficiencies in the supply chain can cause overstocking and stockouts."
        },
        {
          "t": "p",
          "text": "Lack of expertise required to implement and keep up with evolving technologies like AI, IoT, and big data analytics."
        },
        {
          "t": "p",
          "text": "Customers now expect personalized experiences with seamless omnichannel interactions and fast delivery."
        },
        {
          "t": "cta",
          "text": "Request a Call",
          "href": "#pgForm"
        },
        {
          "t": "img",
          "src": "https://azure.folio3.com/wp-content/uploads/2023/11/challenge-faced-retailers-img.webp",
          "w": 697,
          "h": 786,
          "alt": ""
        }
      ],
      "headings": [
        {
          "tag": "h2",
          "text": "Major Challenges Faced by Retailers"
        }
      ],
      "paragraphs": [
        "We believe in the power of the cloud to transform businesses and empower people.",
        "Data stored in silos hinder a comprehensive understanding of operations, market trend, and customer behavior.",
        "Managing a consistent and seamless experience across various channels like online, mobile, and in-store can be challenging.",
        "Inaccurate demand forecasting and inefficiencies in the supply chain can cause overstocking and stockouts.",
        "Lack of expertise required to implement and keep up with evolving technologies like AI, IoT, and big data analytics.",
        "Customers now expect personalized experiences with seamless omnichannel interactions and fast delivery."
      ],
      "listItems": [],
      "ctas": [
        {
          "text": "Request a Call",
          "href": "#pgForm"
        }
      ],
      "images": [
        {
          "src": "https://azure.folio3.com/wp-content/uploads/2023/11/challenge-faced-retailers-img.webp",
          "alt": "",
          "w": 697,
          "h": 786
        }
      ]
    },
    {
      "items": [
        {
          "t": "h",
          "tag": "h2",
          "text": "Powerful Solutions to Meet Your Specific Business Needs"
        },
        {
          "t": "h",
          "tag": "h3",
          "text": "360° View of Customer Data"
        },
        {
          "t": "p",
          "text": "Centralize customer, product, and supplier data into a unified data platform hosted on Azure. This facilitates precise forecasting, efficient inventory planning, cohesive omni-channel customer interactions, and streamlined post-sales and returns management."
        },
        {
          "t": "h",
          "tag": "h3",
          "text": "Enhanced Customer Engagement"
        },
        {
          "t": "p",
          "text": "Centralized customer information allows you to provide personalized assistance, leading to improved customer interactions and loyalty."
        },
        {
          "t": "h",
          "tag": "h3",
          "text": "Streamlined Interactions"
        },
        {
          "t": "p",
          "text": "A holistic view of customer data enables seamless communication and collaboration among employees, ensuring consistent service across departments."
        },
        {
          "t": "h",
          "tag": "h3",
          "text": "Informed Decision-Making"
        },
        {
          "t": "p",
          "text": "Access to complete customer data empowers you to make data-driven decisions, resulting in more effective sales, marketing, and support strategies."
        },
        {
          "t": "cta",
          "text": "Find Out More",
          "href": "#pgForm"
        },
        {
          "t": "img",
          "src": "https://azure.folio3.com/wp-content/uploads/2023/11/360-customer-data.webp",
          "w": 715,
          "h": 620,
          "alt": ""
        },
        {
          "t": "h",
          "tag": "h3",
          "text": "Demand Forecasting"
        },
        {
          "t": "p",
          "text": "Based on your historical data, predict more accurate business outcomes by planning product demand, resources, and inventories. This will help in cost reduction, effective staffing, aligned marketing strategies, and enhanced customer satisfaction."
        },
        {
          "t": "h",
          "tag": "h3",
          "text": "Optimized Inventory Management"
        },
        {
          "t": "p",
          "text": "Minimize inventory carrying costs, reduce stockouts, and ensure products are available when customers want them."
        },
        {
          "t": "h",
          "tag": "h3",
          "text": "Efficient Resource Allocation"
        },
        {
          "t": "p",
          "text": "Retailers can allocate resources effectively based on predicted demand, from inventory to staffing, leading to cost savings and improved operational efficiency."
        },
        {
          "t": "h",
          "tag": "h3",
          "text": "Responsive Marketing"
        },
        {
          "t": "p",
          "text": "Demand forecasting enables retailers to align marketing strategies with expected demand trends, enhancing the effectiveness of campaigns and promotions."
        },
        {
          "t": "cta",
          "text": "Learn More",
          "href": "#pgForm"
        },
        {
          "t": "img",
          "src": "https://azure.folio3.com/wp-content/uploads/2023/11/demand-forecasting-img.webp",
          "w": 243,
          "h": 150,
          "alt": ""
        },
        {
          "t": "h",
          "tag": "h3",
          "text": "Supply Chain Optimization"
        },
        {
          "t": "p",
          "text": "Improve your supply chain efficiency and elevate product and service delivery through advanced insights and analytics that enhance planning, optimize fulfillment, streamline sourcing, and enhance logistics."
        },
        {
          "t": "h",
          "tag": "h3",
          "text": "Inventory Management"
        },
        {
          "t": "p",
          "text": "Optimizing the supply chain through data-driven insights minimizes disruptions, ensuring a steady flow of products and preventing delays or stockouts."
        },
        {
          "t": "h",
          "tag": "h3",
          "text": "Improved Collaboration"
        },
        {
          "t": "p",
          "text": "Data sharing and analytics across the supply chain improve collaboration with stakeholders, resulting in better SKU sourcing, assortment. distribution."
        },
        {
          "t": "h",
          "tag": "h3",
          "text": "Enhanced Efficiency"
        },
        {
          "t": "p",
          "text": "Supply chain optimization reduces excess inventory, transportation costs, and overall supply chain complexities, leading to improved efficiency and cost savings."
        },
        {
          "t": "cta",
          "text": "Find Out More",
          "href": "#pgForm"
        },
        {
          "t": "img",
          "src": "https://azure.folio3.com/wp-content/uploads/2023/11/supply-chain-optimization.webp",
          "w": 278,
          "h": 150,
          "alt": ""
        },
        {
          "t": "h",
          "tag": "h3",
          "text": "Data Security & Compliance"
        },
        {
          "t": "p",
          "text": "Safeguard customer account information, including credit card numbers, account passwords, and contact information. Leverage advanced security features including data encryption, threat detection, and identity management to secure your sensitive data."
        },
        {
          "t": "h",
          "tag": "h3",
          "text": "Data Protection"
        },
        {
          "t": "p",
          "text": "Robust security features protect customer data, preventing data breaches and maintaining customer trust."
        },
        {
          "t": "h",
          "tag": "h3",
          "text": "Regulatory Compliance"
        },
        {
          "t": "p",
          "text": "Implement GDPR and PCI DSS compliant security measures avoiding legal issues and penalties."
        },
        {
          "t": "h",
          "tag": "h3",
          "text": "Fraud Detection"
        },
        {
          "t": "p",
          "text": "Identify unusual patterns in transactions, helping retailers detect and prevent fraudulent activities in real time."
        },
        {
          "t": "cta",
          "text": "Find Out More",
          "href": "#pgForm"
        },
        {
          "t": "img",
          "src": "https://azure.folio3.com/wp-content/uploads/2023/11/data-security-compliance-img.webp",
          "w": 233,
          "h": 150,
          "alt": ""
        },
        {
          "t": "h",
          "tag": "h3",
          "text": "Big Data Analytics & AI/ML"
        },
        {
          "t": "p",
          "text": "Acquire valuable business and customer insights by analyzing data from multiple sources including POS systems, transactions, customer purchase histories, customer demographics, inventory, customer reviews, and social media."
        },
        {
          "t": "h",
          "tag": "h3",
          "text": "Near Real-Time Analytics"
        },
        {
          "t": "p",
          "text": "Monitor sales, inventories, and customer interactions in real time to enable timely decision making and quick responses to changing market trends."
        },
        {
          "t": "h",
          "tag": "h3",
          "text": "Optimize pricing Strategies"
        },
        {
          "t": "p",
          "text": "Analyze product demand in individual customer segments, customer shopping behavior, competitive pricing, and market trends to set optimal pricing strategies that maximize revenue."
        },
        {
          "t": "h",
          "tag": "h3",
          "text": "Personalized Experiences"
        },
        {
          "t": "p",
          "text": "AI-powered analytics enable retailers to identify opportunities for personalized marketing, recommendations, and customer interactions, enhancing engagement and loyalty."
        },
        {
          "t": "cta",
          "text": "Find Out More",
          "href": "#pgForm"
        },
        {
          "t": "img",
          "src": "https://azure.folio3.com/wp-content/uploads/2023/11/big-data-analytics-img.webp",
          "w": 244,
          "h": 150,
          "alt": ""
        },
        {
          "t": "h",
          "tag": "h3",
          "text": "Innovate with IOT"
        },
        {
          "t": "p",
          "text": "Enable smart retailing with seamless, smart, and secure retail technology solutions to engage customers and empower workers. Increase Customer satisfaction by bringing an enjoyable retail experience."
        },
        {
          "t": "h",
          "tag": "h3",
          "text": "Supply Chain Visibility"
        },
        {
          "t": "p",
          "text": "IoT-based tracking enhances supply chain visibility, ensuring products are traced and monitored throughout the entire distribution process."
        },
        {
          "t": "h",
          "tag": "h3",
          "text": "Smart Store Operations"
        },
        {
          "t": "p",
          "text": "IoT sensors in stores can monitor foot traffic, customer behavior, and product interactions. This data helps retailers optimize store layouts, improve merchandising strategies, and enhance customer experiences."
        },
        {
          "t": "h",
          "tag": "h3",
          "text": "Digital Distribution Center"
        },
        {
          "t": "p",
          "text": "Achieve cost reduction, operational efficiency, and uninterrupted operations within your warehouses. Establish digital connectivity to monitor critical assets and operations across automated distribution and fulfillment centers, enabling the extraction of valuable insights for informed actions."
        },
        {
          "t": "cta",
          "text": "Find Out More",
          "href": "#pgForm"
        },
        {
          "t": "img",
          "src": "https://azure.folio3.com/wp-content/uploads/2023/11/innovate-IOT-img.webp",
          "w": 221,
          "h": 150,
          "alt": ""
        },
        {
          "t": "h",
          "tag": "h3",
          "text": "Omni-channel optimization"
        },
        {
          "t": "p",
          "text": "Deliver a cohesive customer journey that empowers shoppers to transition effortlessly between platforms, devices, and channels, all while enjoying a unified multichannel retail experience."
        },
        {
          "t": "h",
          "tag": "h3",
          "text": "Consistent Customer Experience"
        },
        {
          "t": "p",
          "text": "Regardless of the channel customers use (online, in-store, mobile), omni-channel optimization ensures a consistent and seamless experience. This leads to higher customer satisfaction and loyalty."
        },
        {
          "t": "h",
          "tag": "h3",
          "text": "Higher Conversion Rates"
        },
        {
          "t": "p",
          "text": "Providing customers with a variety of engagement points leads to higher conversion rates, as customers can complete purchases on their preferred platforms."
        },
        {
          "t": "h",
          "tag": "h3",
          "text": "Improved Customer Insights"
        },
        {
          "t": "p",
          "text": "An omni-channel approach provides you with a holistic view of customer interactions, enabling deeper insights into behavior and preferences."
        },
        {
          "t": "cta",
          "text": "Find Out More",
          "href": "#pgForm"
        },
        {
          "t": "img",
          "src": "https://azure.folio3.com/wp-content/uploads/2023/11/Omni-channel-optimization-img.webp",
          "w": 201,
          "h": 150,
          "alt": ""
        },
        {
          "t": "h",
          "tag": "h3",
          "text": "AI & Personalization Engines"
        },
        {
          "t": "p",
          "text": "Leverage AI to deliver personalized user experience by generating personalized offers and recommendations that enhance over time with customer behavior. Enhance homepage engagement, personalize channels, and optimize coupon usage using AI."
        },
        {
          "t": "h",
          "tag": "h3",
          "text": "Tailored Recommendations"
        },
        {
          "t": "p",
          "text": "AI-powered personalization engines analyze customer data to provide accurate product recommendations, increasing the likelihood of sales."
        },
        {
          "t": "h",
          "tag": "h3",
          "text": "Enhanced Customer Engagement"
        },
        {
          "t": "p",
          "text": "Personalized experiences foster stronger customer relationships and engagement, leading to repeat business and positive reviews."
        },
        {
          "t": "h",
          "tag": "h3",
          "text": "Higher Conversion Rates"
        },
        {
          "t": "p",
          "text": "Tailoring marketing messages and offers based on individual preferences drives higher conversion rates and boosts overall sales performance."
        },
        {
          "t": "cta",
          "text": "Find Out More",
          "href": "#pgForm"
        },
        {
          "t": "img",
          "src": "https://azure.folio3.com/wp-content/uploads/2023/11/AI-personalized-engines-img.webp",
          "w": 169,
          "h": 150,
          "alt": ""
        }
      ],
      "headings": [
        {
          "tag": "h2",
          "text": "Powerful Solutions to Meet Your Specific Business Needs"
        },
        {
          "tag": "h3",
          "text": "360° View of Customer Data"
        },
        {
          "tag": "h3",
          "text": "Enhanced Customer Engagement"
        },
        {
          "tag": "h3",
          "text": "Streamlined Interactions"
        },
        {
          "tag": "h3",
          "text": "Informed Decision-Making"
        },
        {
          "tag": "h3",
          "text": "Demand Forecasting"
        },
        {
          "tag": "h3",
          "text": "Optimized Inventory Management"
        },
        {
          "tag": "h3",
          "text": "Efficient Resource Allocation"
        },
        {
          "tag": "h3",
          "text": "Responsive Marketing"
        },
        {
          "tag": "h3",
          "text": "Supply Chain Optimization"
        },
        {
          "tag": "h3",
          "text": "Inventory Management"
        },
        {
          "tag": "h3",
          "text": "Improved Collaboration"
        },
        {
          "tag": "h3",
          "text": "Enhanced Efficiency"
        },
        {
          "tag": "h3",
          "text": "Data Security & Compliance"
        },
        {
          "tag": "h3",
          "text": "Data Protection"
        },
        {
          "tag": "h3",
          "text": "Regulatory Compliance"
        },
        {
          "tag": "h3",
          "text": "Fraud Detection"
        },
        {
          "tag": "h3",
          "text": "Big Data Analytics & AI/ML"
        },
        {
          "tag": "h3",
          "text": "Near Real-Time Analytics"
        },
        {
          "tag": "h3",
          "text": "Optimize pricing Strategies"
        },
        {
          "tag": "h3",
          "text": "Personalized Experiences"
        },
        {
          "tag": "h3",
          "text": "Innovate with IOT"
        },
        {
          "tag": "h3",
          "text": "Supply Chain Visibility"
        },
        {
          "tag": "h3",
          "text": "Smart Store Operations"
        },
        {
          "tag": "h3",
          "text": "Digital Distribution Center"
        },
        {
          "tag": "h3",
          "text": "Omni-channel optimization"
        },
        {
          "tag": "h3",
          "text": "Consistent Customer Experience"
        },
        {
          "tag": "h3",
          "text": "Higher Conversion Rates"
        },
        {
          "tag": "h3",
          "text": "Improved Customer Insights"
        },
        {
          "tag": "h3",
          "text": "AI & Personalization Engines"
        },
        {
          "tag": "h3",
          "text": "Tailored Recommendations"
        },
        {
          "tag": "h3",
          "text": "Enhanced Customer Engagement"
        },
        {
          "tag": "h3",
          "text": "Higher Conversion Rates"
        }
      ],
      "paragraphs": [
        "Centralize customer, product, and supplier data into a unified data platform hosted on Azure. This facilitates precise forecasting, efficient inventory planning, cohesive omni-channel customer interactions, and streamlined post-sales and returns management.",
        "Centralized customer information allows you to provide personalized assistance, leading to improved customer interactions and loyalty.",
        "A holistic view of customer data enables seamless communication and collaboration among employees, ensuring consistent service across departments.",
        "Access to complete customer data empowers you to make data-driven decisions, resulting in more effective sales, marketing, and support strategies.",
        "Based on your historical data, predict more accurate business outcomes by planning product demand, resources, and inventories. This will help in cost reduction, effective staffing, aligned marketing strategies, and enhanced customer satisfaction.",
        "Minimize inventory carrying costs, reduce stockouts, and ensure products are available when customers want them.",
        "Retailers can allocate resources effectively based on predicted demand, from inventory to staffing, leading to cost savings and improved operational efficiency.",
        "Demand forecasting enables retailers to align marketing strategies with expected demand trends, enhancing the effectiveness of campaigns and promotions.",
        "Improve your supply chain efficiency and elevate product and service delivery through advanced insights and analytics that enhance planning, optimize fulfillment, streamline sourcing, and enhance logistics.",
        "Optimizing the supply chain through data-driven insights minimizes disruptions, ensuring a steady flow of products and preventing delays or stockouts.",
        "Data sharing and analytics across the supply chain improve collaboration with stakeholders, resulting in better SKU sourcing, assortment. distribution.",
        "Supply chain optimization reduces excess inventory, transportation costs, and overall supply chain complexities, leading to improved efficiency and cost savings.",
        "Safeguard customer account information, including credit card numbers, account passwords, and contact information. Leverage advanced security features including data encryption, threat detection, and identity management to secure your sensitive data.",
        "Robust security features protect customer data, preventing data breaches and maintaining customer trust.",
        "Implement GDPR and PCI DSS compliant security measures avoiding legal issues and penalties.",
        "Identify unusual patterns in transactions, helping retailers detect and prevent fraudulent activities in real time.",
        "Acquire valuable business and customer insights by analyzing data from multiple sources including POS systems, transactions, customer purchase histories, customer demographics, inventory, customer reviews, and social media.",
        "Monitor sales, inventories, and customer interactions in real time to enable timely decision making and quick responses to changing market trends.",
        "Analyze product demand in individual customer segments, customer shopping behavior, competitive pricing, and market trends to set optimal pricing strategies that maximize revenue.",
        "AI-powered analytics enable retailers to identify opportunities for personalized marketing, recommendations, and customer interactions, enhancing engagement and loyalty.",
        "Enable smart retailing with seamless, smart, and secure retail technology solutions to engage customers and empower workers. Increase Customer satisfaction by bringing an enjoyable retail experience.",
        "IoT-based tracking enhances supply chain visibility, ensuring products are traced and monitored throughout the entire distribution process.",
        "IoT sensors in stores can monitor foot traffic, customer behavior, and product interactions. This data helps retailers optimize store layouts, improve merchandising strategies, and enhance customer experiences.",
        "Achieve cost reduction, operational efficiency, and uninterrupted operations within your warehouses. Establish digital connectivity to monitor critical assets and operations across automated distribution and fulfillment centers, enabling the extraction of valuable insights for informed actions.",
        "Deliver a cohesive customer journey that empowers shoppers to transition effortlessly between platforms, devices, and channels, all while enjoying a unified multichannel retail experience.",
        "Regardless of the channel customers use (online, in-store, mobile), omni-channel optimization ensures a consistent and seamless experience. This leads to higher customer satisfaction and loyalty.",
        "Providing customers with a variety of engagement points leads to higher conversion rates, as customers can complete purchases on their preferred platforms.",
        "An omni-channel approach provides you with a holistic view of customer interactions, enabling deeper insights into behavior and preferences.",
        "Leverage AI to deliver personalized user experience by generating personalized offers and recommendations that enhance over time with customer behavior. Enhance homepage engagement, personalize channels, and optimize coupon usage using AI.",
        "AI-powered personalization engines analyze customer data to provide accurate product recommendations, increasing the likelihood of sales.",
        "Personalized experiences foster stronger customer relationships and engagement, leading to repeat business and positive reviews.",
        "Tailoring marketing messages and offers based on individual preferences drives higher conversion rates and boosts overall sales performance."
      ],
      "listItems": [],
      "ctas": [
        {
          "text": "Find Out More",
          "href": "#pgForm"
        },
        {
          "text": "Learn More",
          "href": "#pgForm"
        },
        {
          "text": "Find Out More",
          "href": "#pgForm"
        },
        {
          "text": "Find Out More",
          "href": "#pgForm"
        },
        {
          "text": "Find Out More",
          "href": "#pgForm"
        },
        {
          "text": "Find Out More",
          "href": "#pgForm"
        },
        {
          "text": "Find Out More",
          "href": "#pgForm"
        },
        {
          "text": "Find Out More",
          "href": "#pgForm"
        }
      ],
      "images": [
        {
          "src": "https://azure.folio3.com/wp-content/uploads/2023/11/360-customer-data.webp",
          "alt": "",
          "w": 715,
          "h": 620
        },
        {
          "src": "https://azure.folio3.com/wp-content/uploads/2023/11/demand-forecasting-img.webp",
          "alt": "",
          "w": 243,
          "h": 150
        },
        {
          "src": "https://azure.folio3.com/wp-content/uploads/2023/11/supply-chain-optimization.webp",
          "alt": "",
          "w": 278,
          "h": 150
        },
        {
          "src": "https://azure.folio3.com/wp-content/uploads/2023/11/data-security-compliance-img.webp",
          "alt": "",
          "w": 233,
          "h": 150
        },
        {
          "src": "https://azure.folio3.com/wp-content/uploads/2023/11/big-data-analytics-img.webp",
          "alt": "",
          "w": 244,
          "h": 150
        },
        {
          "src": "https://azure.folio3.com/wp-content/uploads/2023/11/innovate-IOT-img.webp",
          "alt": "",
          "w": 221,
          "h": 150
        },
        {
          "src": "https://azure.folio3.com/wp-content/uploads/2023/11/Omni-channel-optimization-img.webp",
          "alt": "",
          "w": 201,
          "h": 150
        },
        {
          "src": "https://azure.folio3.com/wp-content/uploads/2023/11/AI-personalized-engines-img.webp",
          "alt": "",
          "w": 169,
          "h": 150
        }
      ]
    },
    {
      "items": [
        {
          "t": "h",
          "tag": "h3",
          "text": "Redefine Customer Journeys, Unify Channels, and Drive AI-Powered Personalization Strategies."
        },
        {
          "t": "cta",
          "text": "Take the Leap Now",
          "href": "#pgForm"
        },
        {
          "t": "img",
          "src": "https://azure.folio3.com/wp-content/uploads/2023/11/redefine-customer-img.webp",
          "w": 571,
          "h": 494,
          "alt": ""
        }
      ],
      "headings": [
        {
          "tag": "h3",
          "text": "Redefine Customer Journeys, Unify Channels, and Drive AI-Powered Personalization Strategies."
        }
      ],
      "paragraphs": [],
      "listItems": [],
      "ctas": [
        {
          "text": "Take the Leap Now",
          "href": "#pgForm"
        }
      ],
      "images": [
        {
          "src": "https://azure.folio3.com/wp-content/uploads/2023/11/redefine-customer-img.webp",
          "alt": "",
          "w": 571,
          "h": 494
        }
      ]
    },
    {
      "items": [
        {
          "t": "h",
          "tag": "h2",
          "text": "Folio3 Approach to Azure Services"
        },
        {
          "t": "p",
          "text": "Find a partnership that helps you achieve more for your people, your business and your customers."
        },
        {
          "t": "h",
          "tag": "h3",
          "text": "Consulting and Advisory Services"
        },
        {
          "t": "p",
          "text": "Leverage our team of Azure experts to help you define the right strategy for your cloud journey Learn More > >"
        },
        {
          "t": "h",
          "tag": "h3",
          "text": "Cloud Services"
        },
        {
          "t": "p",
          "text": "We’ll design, build, and deploy solutions that help you get the most out of your applications Learn More > >"
        },
        {
          "t": "h",
          "tag": "h3",
          "text": "Managed Services"
        },
        {
          "t": "p",
          "text": "Dedicated retail professionals who help you manage, operate, and optimize your data-to-day elements of cloud environment Learn More > >"
        },
        {
          "t": "h",
          "tag": "h3",
          "text": "Data Analytics Services"
        },
        {
          "t": "p",
          "text": "Let us empower you to leverage the full power of your data and turn it into insights to drive retail business growth Learn More > >"
        }
      ],
      "headings": [
        {
          "tag": "h2",
          "text": "Folio3 Approach to Azure Services"
        },
        {
          "tag": "h3",
          "text": "Consulting and Advisory Services"
        },
        {
          "tag": "h3",
          "text": "Cloud Services"
        },
        {
          "tag": "h3",
          "text": "Managed Services"
        },
        {
          "tag": "h3",
          "text": "Data Analytics Services"
        }
      ],
      "paragraphs": [
        "Find a partnership that helps you achieve more for your people, your business and your customers.",
        "Leverage our team of Azure experts to help you define the right strategy for your cloud journey Learn More > >",
        "We’ll design, build, and deploy solutions that help you get the most out of your applications Learn More > >",
        "Dedicated retail professionals who help you manage, operate, and optimize your data-to-day elements of cloud environment Learn More > >",
        "Let us empower you to leverage the full power of your data and turn it into insights to drive retail business growth Learn More > >"
      ],
      "listItems": [],
      "ctas": [],
      "images": []
    },
    {
      "items": [
        {
          "t": "h",
          "tag": "h3",
          "text": "Awards & Recognization"
        },
        {
          "t": "img",
          "src": "https://azure.folio3.com/wp-content/uploads/2023/11/azure_solution_architect.svg",
          "w": 150,
          "h": 150,
          "alt": "azure_solution_architect.svg"
        },
        {
          "t": "img",
          "src": "https://azure.folio3.com/wp-content/uploads/2023/11/azure_administration.svg",
          "w": 150,
          "h": 150,
          "alt": "azure_administration.svg"
        },
        {
          "t": "img",
          "src": "https://azure.folio3.com/wp-content/uploads/2023/11/AZ-400-104-or-204-Azure-DevOps-Engineer-Expert.svg",
          "w": 150,
          "h": 150,
          "alt": "AZ-400-104-or-204-Azure-DevOps-Engineer-Expert.svg"
        },
        {
          "t": "img",
          "src": "https://azure.folio3.com/wp-content/uploads/2023/11/azure_security_engineer.svg",
          "w": 150,
          "h": 150,
          "alt": "azure_security_engineer.svg"
        },
        {
          "t": "img",
          "src": "https://azure.folio3.com/wp-content/uploads/2023/11/data-analyst.svg",
          "w": 150,
          "h": 150,
          "alt": "data-analyst.svg"
        },
        {
          "t": "img",
          "src": "https://azure.folio3.com/wp-content/uploads/2023/11/azure-data-engineer.svg",
          "w": 151,
          "h": 150,
          "alt": "azure-data-engineer.svg"
        },
        {
          "t": "img",
          "src": "https://azure.folio3.com/wp-content/uploads/2023/11/power_platform_developers.svg",
          "w": 150,
          "h": 150,
          "alt": "power_platform_developers.svg"
        },
        {
          "t": "img",
          "src": "https://azure.folio3.com/wp-content/uploads/2023/11/azure-network-engineer.svg",
          "w": 150,
          "h": 150,
          "alt": "azure-network-engineer.svg"
        },
        {
          "t": "img",
          "src": "https://azure.folio3.com/wp-content/uploads/2023/11/MB-900.svg",
          "w": 150,
          "h": 150,
          "alt": "MB-900.svg"
        },
        {
          "t": "img",
          "src": "https://azure.folio3.com/wp-content/uploads/2023/11/AI-102.svg",
          "w": 150,
          "h": 150,
          "alt": "AI-102.svg"
        },
        {
          "t": "img",
          "src": "https://azure.folio3.com/wp-content/uploads/2023/11/DP-100.svg",
          "w": 150,
          "h": 150,
          "alt": "DP-100.svg"
        },
        {
          "t": "img",
          "src": "https://azure.folio3.com/wp-content/uploads/2023/11/AZ-140.svg",
          "w": 150,
          "h": 150,
          "alt": "AZ-140.svg"
        },
        {
          "t": "img",
          "src": "https://azure.folio3.com/wp-content/uploads/2023/11/azure-stack-hub.svg",
          "w": 151,
          "h": 150,
          "alt": "azure-stack-hub.svg"
        },
        {
          "t": "img",
          "src": "https://azure.folio3.com/wp-content/uploads/2023/11/window-server-hybrid-administration.svg",
          "w": 150,
          "h": 150,
          "alt": "window-server-hybrid-administration.svg"
        },
        {
          "t": "img",
          "src": "https://azure.folio3.com/wp-content/uploads/2023/11/mirosoft_certified_trainer.svg",
          "w": 150,
          "h": 150,
          "alt": "mirosoft_certified_trainer.svg"
        }
      ],
      "headings": [
        {
          "tag": "h3",
          "text": "Awards & Recognization"
        }
      ],
      "paragraphs": [],
      "listItems": [],
      "ctas": [],
      "images": [
        {
          "src": "https://azure.folio3.com/wp-content/uploads/2023/11/azure_solution_architect.svg",
          "alt": "azure_solution_architect.svg",
          "w": 150,
          "h": 150
        },
        {
          "src": "https://azure.folio3.com/wp-content/uploads/2023/11/azure_administration.svg",
          "alt": "azure_administration.svg",
          "w": 150,
          "h": 150
        },
        {
          "src": "https://azure.folio3.com/wp-content/uploads/2023/11/AZ-400-104-or-204-Azure-DevOps-Engineer-Expert.svg",
          "alt": "AZ-400-104-or-204-Azure-DevOps-Engineer-Expert.svg",
          "w": 150,
          "h": 150
        },
        {
          "src": "https://azure.folio3.com/wp-content/uploads/2023/11/azure_security_engineer.svg",
          "alt": "azure_security_engineer.svg",
          "w": 150,
          "h": 150
        },
        {
          "src": "https://azure.folio3.com/wp-content/uploads/2023/11/data-analyst.svg",
          "alt": "data-analyst.svg",
          "w": 150,
          "h": 150
        },
        {
          "src": "https://azure.folio3.com/wp-content/uploads/2023/11/azure-data-engineer.svg",
          "alt": "azure-data-engineer.svg",
          "w": 151,
          "h": 150
        },
        {
          "src": "https://azure.folio3.com/wp-content/uploads/2023/11/power_platform_developers.svg",
          "alt": "power_platform_developers.svg",
          "w": 150,
          "h": 150
        },
        {
          "src": "https://azure.folio3.com/wp-content/uploads/2023/11/azure-network-engineer.svg",
          "alt": "azure-network-engineer.svg",
          "w": 150,
          "h": 150
        },
        {
          "src": "https://azure.folio3.com/wp-content/uploads/2023/11/MB-900.svg",
          "alt": "MB-900.svg",
          "w": 150,
          "h": 150
        },
        {
          "src": "https://azure.folio3.com/wp-content/uploads/2023/11/AI-102.svg",
          "alt": "AI-102.svg",
          "w": 150,
          "h": 150
        },
        {
          "src": "https://azure.folio3.com/wp-content/uploads/2023/11/DP-100.svg",
          "alt": "DP-100.svg",
          "w": 150,
          "h": 150
        },
        {
          "src": "https://azure.folio3.com/wp-content/uploads/2023/11/AZ-140.svg",
          "alt": "AZ-140.svg",
          "w": 150,
          "h": 150
        },
        {
          "src": "https://azure.folio3.com/wp-content/uploads/2023/11/azure-stack-hub.svg",
          "alt": "azure-stack-hub.svg",
          "w": 151,
          "h": 150
        },
        {
          "src": "https://azure.folio3.com/wp-content/uploads/2023/11/window-server-hybrid-administration.svg",
          "alt": "window-server-hybrid-administration.svg",
          "w": 150,
          "h": 150
        },
        {
          "src": "https://azure.folio3.com/wp-content/uploads/2023/11/mirosoft_certified_trainer.svg",
          "alt": "mirosoft_certified_trainer.svg",
          "w": 150,
          "h": 150
        }
      ]
    },
    {
      "items": [
        {
          "t": "h",
          "tag": "h2",
          "text": "Why Choose Folio3?"
        },
        {
          "t": "p",
          "text": "We believe in the power of the cloud to transform businesses and empower people."
        },
        {
          "t": "img",
          "src": "https://azure.folio3.com/wp-content/uploads/2023/11/about_us-mock.webp",
          "w": 200,
          "h": 150,
          "alt": ""
        },
        {
          "t": "li",
          "text": "Over 15 years in custom software development"
        },
        {
          "t": "li",
          "text": "Microsoft Business Solutions Partner in Cloud Solutions"
        },
        {
          "t": "li",
          "text": "We are a team of professionals, well-versed in industry processes and regulations, as well as the implementation of Azure technologies such as AI/ML, Big Data, and Cloud services."
        }
      ],
      "headings": [
        {
          "tag": "h2",
          "text": "Why Choose Folio3?"
        }
      ],
      "paragraphs": [
        "We believe in the power of the cloud to transform businesses and empower people."
      ],
      "listItems": [
        "Over 15 years in custom software development",
        "Microsoft Business Solutions Partner in Cloud Solutions",
        "We are a team of professionals, well-versed in industry processes and regulations, as well as the implementation of Azure technologies such as AI/ML, Big Data, and Cloud services."
      ],
      "ctas": [],
      "images": [
        {
          "src": "https://azure.folio3.com/wp-content/uploads/2023/11/about_us-mock.webp",
          "alt": "",
          "w": 200,
          "h": 150
        }
      ]
    },
    {
      "items": [
        {
          "t": "h",
          "tag": "h2",
          "text": "Real Results, Real Impact,"
        },
        {
          "t": "p",
          "text": "See How Our Customers Succeed"
        },
        {
          "t": "h",
          "tag": "h3",
          "text": "Savills"
        },
        {
          "t": "h",
          "tag": "h3",
          "text": "Savills"
        },
        {
          "t": "cta",
          "text": "Read More",
          "href": "/savills/"
        },
        {
          "t": "h",
          "tag": "h3",
          "text": "CityU"
        },
        {
          "t": "h",
          "tag": "h3",
          "text": "CityU"
        },
        {
          "t": "cta",
          "text": "Read More",
          "href": "/city-university-azure/"
        },
        {
          "t": "cta",
          "text": "Discover All",
          "href": "#pgForm"
        }
      ],
      "headings": [
        {
          "tag": "h2",
          "text": "Real Results, Real Impact,"
        },
        {
          "tag": "h3",
          "text": "Savills"
        },
        {
          "tag": "h3",
          "text": "Savills"
        },
        {
          "tag": "h3",
          "text": "CityU"
        },
        {
          "tag": "h3",
          "text": "CityU"
        }
      ],
      "paragraphs": [
        "See How Our Customers Succeed"
      ],
      "listItems": [],
      "ctas": [
        {
          "text": "Read More",
          "href": "/savills/"
        },
        {
          "text": "Read More",
          "href": "/city-university-azure/"
        },
        {
          "text": "Discover All",
          "href": "#pgForm"
        }
      ],
      "images": []
    },
    {
      "items": [
        {
          "t": "h",
          "tag": "h2",
          "text": "Partner with Folio3 to Streamline your Healthcare Business"
        },
        {
          "t": "p",
          "text": "We believe in the power of the cloud to transform businesses and empower people."
        },
        {
          "t": "p",
          "text": "Azure’s Demand Forecasting solution utilizes historical data and AI/ML algorithms to accurately predict demand trends. This helps optimize inventory levels, reduce stockouts, and improve inventory turnover."
        },
        {
          "t": "p",
          "text": "Azure IoT and Azure Analytics solutions collaborate to optimize supply chain processes. Azure IoT Hub enables real-time tracking, while Azure Databricks analyzes data for insights. This enhances supply chain visibility, reduces disruptions, and enables efficient resource allocation."
        },
        {
          "t": "p",
          "text": "Azure provides robust security features, including Azure Security Center and Azure Active Directory, to safeguard customer data. Azure’s compliance certifications, such as GDPR, ensure adherence to regulations and industry standards."
        },
        {
          "t": "p",
          "text": "Azure’s omni-channel optimization tools, powered by Azure IoT and Azure AI, enable consistent experiences across channels. Azure IoT enables real-time insights, while Azure AI personalized interactions, resulting in higher satisfaction and conversion rates."
        },
        {
          "t": "p",
          "text": "Azure Virtual Agents, part of Azure AI, efficiently handle customer inquiries through AI chatbots. These AI agents provide instant responses and insights into customer sentiment, improving customer service quality and freeing up staff for more complex tasks."
        },
        {
          "t": "p",
          "text": "Yes, Azure offers Azure Modernization solutions that encompass application modernization, cloud adoption, and technology upgrades. Azure’s flexibility and tools assist in transforming legacy systems, enhancing customer experiences, and streamlining operations."
        },
        {
          "t": "p",
          "text": "Azure Data Analytics tools, such as Azure Synapse Analytics, process vast customer data sets to uncover actionable insights. These insights into behavior and preferences guide effective decision-making for targeted strategies."
        },
        {
          "t": "p",
          "text": "Azure’s cloud infrastructure provides seamless scalability using Azure Autoscale and Azure Kubernetes Service. These services allow you to adjust resources based on demand, ensuring optimal performance during peak times and efficient resource allocation."
        },
        {
          "t": "img",
          "src": "https://azure.folio3.com/wp-content/uploads/2023/11/ques-ans-img-1.webp",
          "w": 108,
          "h": 150,
          "alt": ""
        }
      ],
      "headings": [
        {
          "tag": "h2",
          "text": "Partner with Folio3 to Streamline your Healthcare Business"
        }
      ],
      "paragraphs": [
        "We believe in the power of the cloud to transform businesses and empower people.",
        "Azure’s Demand Forecasting solution utilizes historical data and AI/ML algorithms to accurately predict demand trends. This helps optimize inventory levels, reduce stockouts, and improve inventory turnover.",
        "Azure IoT and Azure Analytics solutions collaborate to optimize supply chain processes. Azure IoT Hub enables real-time tracking, while Azure Databricks analyzes data for insights. This enhances supply chain visibility, reduces disruptions, and enables efficient resource allocation.",
        "Azure provides robust security features, including Azure Security Center and Azure Active Directory, to safeguard customer data. Azure’s compliance certifications, such as GDPR, ensure adherence to regulations and industry standards.",
        "Azure’s omni-channel optimization tools, powered by Azure IoT and Azure AI, enable consistent experiences across channels. Azure IoT enables real-time insights, while Azure AI personalized interactions, resulting in higher satisfaction and conversion rates.",
        "Azure Virtual Agents, part of Azure AI, efficiently handle customer inquiries through AI chatbots. These AI agents provide instant responses and insights into customer sentiment, improving customer service quality and freeing up staff for more complex tasks.",
        "Yes, Azure offers Azure Modernization solutions that encompass application modernization, cloud adoption, and technology upgrades. Azure’s flexibility and tools assist in transforming legacy systems, enhancing customer experiences, and streamlining operations.",
        "Azure Data Analytics tools, such as Azure Synapse Analytics, process vast customer data sets to uncover actionable insights. These insights into behavior and preferences guide effective decision-making for targeted strategies.",
        "Azure’s cloud infrastructure provides seamless scalability using Azure Autoscale and Azure Kubernetes Service. These services allow you to adjust resources based on demand, ensuring optimal performance during peak times and efficient resource allocation."
      ],
      "listItems": [],
      "ctas": [],
      "images": [
        {
          "src": "https://azure.folio3.com/wp-content/uploads/2023/11/ques-ans-img-1.webp",
          "alt": "",
          "w": 108,
          "h": 150
        }
      ]
    },
    {
      "items": [
        {
          "t": "img",
          "src": "https://azure.folio3.com/wp-content/uploads/2024/08/azure-offices-map-img.webp",
          "w": 283,
          "h": 150,
          "alt": ""
        },
        {
          "t": "h",
          "tag": "h2",
          "text": "Schedule a 1:1 Call Today"
        },
        {
          "t": "h",
          "tag": "h2",
          "text": "Get in touch with our team to solve your Azure queries"
        }
      ],
      "headings": [
        {
          "tag": "h2",
          "text": "Schedule a 1:1 Call Today"
        },
        {
          "tag": "h2",
          "text": "Get in touch with our team to solve your Azure queries"
        }
      ],
      "paragraphs": [],
      "listItems": [],
      "ctas": [],
      "images": [
        {
          "src": "https://azure.folio3.com/wp-content/uploads/2024/08/azure-offices-map-img.webp",
          "alt": "",
          "w": 283,
          "h": 150
        }
      ]
    },
    {
      "items": [
        {
          "t": "img",
          "src": "https://azure.folio3.com/wp-content/uploads/2023/04/azure_logo_ftr.png",
          "w": 300,
          "h": 59,
          "alt": "Azure"
        },
        {
          "t": "h",
          "tag": "h5",
          "text": "US Office"
        },
        {
          "t": "li",
          "text": "160 Bovet Road, Suite # 101, San Mateo, CA 94402 USA"
        },
        {
          "t": "li",
          "text": "Pleasanton, California – 6701 Koll Center Parkway, #250 Pleasanton, CA 94566"
        },
        {
          "t": "li",
          "text": "Tel: +1 408 412-3813"
        },
        {
          "t": "li",
          "text": "Support: +1 (408) 512 1812"
        },
        {
          "t": "h",
          "tag": "h5",
          "text": "UAE OFFICE"
        },
        {
          "t": "li",
          "text": "Dubai, UAE – Dubai Internet City, 1st Floor, Building Number 12, Premises ED 29, Dubai, UAE"
        },
        {
          "t": "li",
          "text": "Tel: +971-55-6540154"
        },
        {
          "t": "li",
          "text": "Tel: +971-04-2505173"
        },
        {
          "t": "h",
          "tag": "h5",
          "text": "UK OFFICE"
        },
        {
          "t": "li",
          "text": "Export House, Cawsey Way, Woking Surrey, GU21 6QX"
        },
        {
          "t": "li",
          "text": "Tel: +44 (0) 14 8361 6611"
        },
        {
          "t": "h",
          "tag": "h5",
          "text": "Mexico Office"
        },
        {
          "t": "li",
          "text": "EPICENTRIA, Avenida Netzahualcóyotl 1597, Ciudad del Sol, Zapopan, Jalisco"
        },
        {
          "t": "h",
          "tag": "h5",
          "text": "Pakistan Office"
        },
        {
          "t": "li",
          "text": "Plot 26, Block B, SMCH Society, Main Shahrah-e-Faisal, Karachi"
        },
        {
          "t": "li",
          "text": "Corporate 7 by Maaksons, Executive Block, Civic Center 1, Gulberg Green, Islamabad"
        },
        {
          "t": "li",
          "text": "First Floor, Blue Mall 8-R, MM Alam Road Gulberg III, Lahore"
        },
        {
          "t": "li",
          "text": "Tel: +92-21-3432 3721-4"
        },
        {
          "t": "h",
          "tag": "h5",
          "text": "Canada Office"
        },
        {
          "t": "li",
          "text": "3080 Yonge Street, Suite 6060, Toronto, Ontario M4N 3N1"
        },
        {
          "t": "li",
          "text": "Tel: +1 408 365 4638"
        },
        {
          "t": "li",
          "text": "Support: +1 (408) 512 1812"
        },
        {
          "t": "h",
          "tag": "h5",
          "text": "Bulgaria Office"
        },
        {
          "t": "li",
          "text": "49 Bacho Kiro Street, Sofia, 1000, Bulgaria"
        },
        {
          "t": "p",
          "text": "© 2026, Folio3 Software Inc., All rights reserved."
        },
        {
          "t": "p",
          "text": "Privacy Policy & Terms of Use Cookie Policy"
        }
      ],
      "headings": [
        {
          "tag": "h5",
          "text": "US Office"
        },
        {
          "tag": "h5",
          "text": "UAE OFFICE"
        },
        {
          "tag": "h5",
          "text": "UK OFFICE"
        },
        {
          "tag": "h5",
          "text": "Mexico Office"
        },
        {
          "tag": "h5",
          "text": "Pakistan Office"
        },
        {
          "tag": "h5",
          "text": "Canada Office"
        },
        {
          "tag": "h5",
          "text": "Bulgaria Office"
        }
      ],
      "paragraphs": [
        "© 2026, Folio3 Software Inc., All rights reserved.",
        "Privacy Policy & Terms of Use Cookie Policy"
      ],
      "listItems": [
        "160 Bovet Road, Suite # 101, San Mateo, CA 94402 USA",
        "Pleasanton, California – 6701 Koll Center Parkway, #250 Pleasanton, CA 94566",
        "Tel: +1 408 412-3813",
        "Support: +1 (408) 512 1812",
        "Dubai, UAE – Dubai Internet City, 1st Floor, Building Number 12, Premises ED 29, Dubai, UAE",
        "Tel: +971-55-6540154",
        "Tel: +971-04-2505173",
        "Export House, Cawsey Way, Woking Surrey, GU21 6QX",
        "Tel: +44 (0) 14 8361 6611",
        "EPICENTRIA, Avenida Netzahualcóyotl 1597, Ciudad del Sol, Zapopan, Jalisco",
        "Plot 26, Block B, SMCH Society, Main Shahrah-e-Faisal, Karachi",
        "Corporate 7 by Maaksons, Executive Block, Civic Center 1, Gulberg Green, Islamabad",
        "First Floor, Blue Mall 8-R, MM Alam Road Gulberg III, Lahore",
        "Tel: +92-21-3432 3721-4",
        "3080 Yonge Street, Suite 6060, Toronto, Ontario M4N 3N1",
        "Tel: +1 408 365 4638",
        "49 Bacho Kiro Street, Sofia, 1000, Bulgaria"
      ],
      "ctas": [],
      "images": [
        {
          "src": "https://azure.folio3.com/wp-content/uploads/2023/04/azure_logo_ftr.png",
          "alt": "Azure",
          "w": 300,
          "h": 59
        }
      ]
    }
  ],
  "images": [
    {
      "src": "https://azure.folio3.com/wp-content/uploads/2022/06/folio3_by_azure.svg",
      "alt": ""
    },
    {
      "src": "https://azure.folio3.com/wp-content/uploads/2023/11/retail-top-banner-img.webp",
      "alt": ""
    },
    {
      "src": "https://azure.folio3.com/wp-content/uploads/2023/11/challenge-faced-retailers-img.webp",
      "alt": ""
    },
    {
      "src": "https://azure.folio3.com/wp-content/uploads/2023/11/360-customer-data.webp",
      "alt": ""
    },
    {
      "src": "https://azure.folio3.com/wp-content/uploads/2023/11/demand-forecasting-img.webp",
      "alt": ""
    },
    {
      "src": "https://azure.folio3.com/wp-content/uploads/2023/11/supply-chain-optimization.webp",
      "alt": ""
    },
    {
      "src": "https://azure.folio3.com/wp-content/uploads/2023/11/data-security-compliance-img.webp",
      "alt": ""
    },
    {
      "src": "https://azure.folio3.com/wp-content/uploads/2023/11/big-data-analytics-img.webp",
      "alt": ""
    },
    {
      "src": "https://azure.folio3.com/wp-content/uploads/2023/11/innovate-IOT-img.webp",
      "alt": ""
    },
    {
      "src": "https://azure.folio3.com/wp-content/uploads/2023/11/Omni-channel-optimization-img.webp",
      "alt": ""
    },
    {
      "src": "https://azure.folio3.com/wp-content/uploads/2023/11/AI-personalized-engines-img.webp",
      "alt": ""
    },
    {
      "src": "https://azure.folio3.com/wp-content/uploads/2023/11/redefine-customer-img.webp",
      "alt": ""
    },
    {
      "src": "https://azure.folio3.com/wp-content/uploads/2023/11/azure_solution_architect.svg",
      "alt": ""
    },
    {
      "src": "https://azure.folio3.com/wp-content/uploads/2023/11/azure_administration.svg",
      "alt": ""
    },
    {
      "src": "https://azure.folio3.com/wp-content/uploads/2023/11/AZ-400-104-or-204-Azure-DevOps-Engineer-Expert.svg",
      "alt": ""
    },
    {
      "src": "https://azure.folio3.com/wp-content/uploads/2023/11/azure_security_engineer.svg",
      "alt": ""
    },
    {
      "src": "https://azure.folio3.com/wp-content/uploads/2023/11/data-analyst.svg",
      "alt": ""
    },
    {
      "src": "https://azure.folio3.com/wp-content/uploads/2023/11/azure-data-engineer.svg",
      "alt": ""
    },
    {
      "src": "https://azure.folio3.com/wp-content/uploads/2023/11/power_platform_developers.svg",
      "alt": ""
    },
    {
      "src": "https://azure.folio3.com/wp-content/uploads/2023/11/azure-network-engineer.svg",
      "alt": ""
    },
    {
      "src": "https://azure.folio3.com/wp-content/uploads/2023/11/MB-900.svg",
      "alt": ""
    },
    {
      "src": "https://azure.folio3.com/wp-content/uploads/2023/11/AI-102.svg",
      "alt": ""
    },
    {
      "src": "https://azure.folio3.com/wp-content/uploads/2023/11/DP-100.svg",
      "alt": ""
    },
    {
      "src": "https://azure.folio3.com/wp-content/uploads/2023/11/AZ-140.svg",
      "alt": ""
    },
    {
      "src": "https://azure.folio3.com/wp-content/uploads/2023/11/azure-stack-hub.svg",
      "alt": ""
    },
    {
      "src": "https://azure.folio3.com/wp-content/uploads/2023/11/window-server-hybrid-administration.svg",
      "alt": ""
    },
    {
      "src": "https://azure.folio3.com/wp-content/uploads/2023/11/mirosoft_certified_trainer.svg",
      "alt": ""
    },
    {
      "src": "https://azure.folio3.com/wp-content/uploads/2023/11/about_us-mock.webp",
      "alt": ""
    },
    {
      "src": "https://azure.folio3.com/wp-content/uploads/2023/11/ques-ans-img-1.webp",
      "alt": ""
    },
    {
      "src": "https://azure.folio3.com/wp-content/uploads/2024/08/azure-offices-map-img.webp",
      "alt": ""
    },
    {
      "src": "https://azure.folio3.com/wp-content/uploads/2023/04/azure_logo_ftr.png",
      "alt": ""
    }
  ],
  "bgImages": [
    "https://azure.folio3.com/wp-content/uploads/2023/11/azure-healthcare-header-bg-1-1-1.webp"
  ]
}